[{"Valor": "R$ 165.531,00", "Marca": "Lexus", "Modelo": "CT200h  1.8 16V Hybrid Aut.", "AnoModelo": 2019, "Combustivel": "Gasolina", "CodigoFipe": "057034-6", "MesReferencia": "agosto de 2022 ", "Autenticacao": "jldwn9yq0tc9z", "TipoVeiculo": 1, "SiglaCombustivel": "G", "DataConsulta": "terça-feira, 4 de abril de 2023 00:29", "codigoTipoVeiculo": 1, "codigoMesReferencia": 288, "codigoMarca": 34, "codigoModelo": 6297, "codigoTipoCombustivel": 1}, {"Valor": "R$ 123.954,00", "Marca": "Lexus", "Modelo": "CT200h  1.8 16V Hybrid Aut.", "AnoModelo": 2018, "Combustivel": "Gasolina", "CodigoFipe": "057034-6", "MesReferencia": "agosto de 2022 ", "Autenticacao": "g0npj9cmjqc6r", "TipoVeiculo": 1, "SiglaCombustivel": "G", "DataConsulta": "terça-feira, 4 de abril de 2023 00:29", "codigoTipoVeiculo": 1, "codigoMesReferencia": 288, "codigoMarca": 34, "codigoModelo": 6297, "codigoTipoCombustivel": 1}, {"Valor": "R$ 106.014,00", "Marca": "Lexus", "Modelo": "CT200h  1.8 16V Hybrid Aut.", "AnoModelo": 2017, "Combustivel": "Gasolina", "CodigoFipe": "057034-6", "MesReferencia": "agosto de 2022 ", "Autenticacao": "gbmmj8qq7cc3j", "TipoVeiculo": 1, "SiglaCombustivel": "G", "DataConsulta": "terça-feira, 4 de abril de 2023 00:29", "codigoTipoVeiculo": 1, "codigoMesReferencia": 288, "codigoMarca": 34, "codigoModelo": 6297, "codigoTipoCombustivel": 1}, {"Valor": "R$ 100.065,00", "Marca": "Lexus", "Modelo": "CT200h  1.8 16V Hybrid Aut.", "AnoModelo": 2016, "Combustivel": "Gasolina", "CodigoFipe": "057034-6", "MesReferencia": "agosto de 2022 ", "Autenticacao": "f3ndg2pt9xcz9", "TipoVeiculo": 1, "SiglaCombustivel": "G", "DataConsulta": "terça-feira, 4 de abril de 2023 00:29", "codigoTipoVeiculo": 1, "codigoMesReferencia": 288, "codigoMarca": 34, "codigoModelo": 6297, "codigoTipoCombustivel": 1}, {"Valor": "R$ 90.330,00", "Marca": "Lexus", "Modelo": "CT200h  1.8 16V Hybrid Aut.", "AnoModelo": 2015, "Combustivel": "Gasolina", "CodigoFipe": "057034-6", "MesReferencia": "agosto de 2022 ", "Autenticacao": "cfhfm5lwy80vt", "TipoVeiculo": 1, "SiglaCombustivel": "G", "DataConsulta": "terça-feira, 4 de abril de 2023 00:29", "codigoTipoVeiculo": 1, "codigoMesReferencia": 288, "codigoMarca": 34, "codigoModelo": 6297, "codigoTipoCombustivel": 1}, {"Valor": "R$ 87.428,00", "Marca": "Lexus", "Modelo": "CT200h  1.8 16V Hybrid Aut.", "AnoModelo": 2014, "Combustivel": "Gasolina", "CodigoFipe": "057034-6", "MesReferencia": "agosto de 2022 ", "Autenticacao": "cdddvqgrc8yrl", "TipoVeiculo": 1, "SiglaCombustivel": "G", "DataConsulta": "terça-feira, 4 de abril de 2023 00:29", "codigoTipoVeiculo": 1, "codigoMesReferencia": 288, "codigoMarca": 34, "codigoModelo": 6297, "codigoTipoCombustivel": 1}, {"Valor": "R$ 70.448,00", "Marca": "Lexus", "Modelo": "CT200h  1.8 16V Hybrid Aut.", "AnoModelo": 2013, "Combustivel": "Gasolina", "CodigoFipe": "057034-6", "MesReferencia": "agosto de 2022 ", "Autenticacao": "5y94ktgwz7nc", "TipoVeiculo": 1, "SiglaCombustivel": "G", "DataConsulta": "terça-feira, 4 de abril de 2023 00:29", "codigoTipoVeiculo": 1, "codigoMesReferencia": 288, "codigoMarca": 34, "codigoModelo": 6297, "codigoTipoCombustivel": 1}, {"Valor": "R$ 107.274,00", "Marca": "Lexus", "Modelo": "CT200h F-Sport 1.8 16V Hybrid Aut.", "AnoModelo": 2013, "Combustivel": "Gasolina", "CodigoFipe": "057035-4", "MesReferencia": "agosto de 2022 ", "Autenticacao": "gc3d8cchhxcpm", "TipoVeiculo": 1, "SiglaCombustivel": "G", "DataConsulta": "terça-feira, 4 de abril de 2023 00:29", "codigoTipoVeiculo": 1, "codigoMesReferencia": 288, "codigoMarca": 34, "codigoModelo": 6298, "codigoTipoCombustivel": 1}, {"Valor": "R$ 350.998,00", "Marca": "Lexus", "Modelo": "ES300h 2.5 16V Aut. (Hybrid)", "AnoModelo": 32000, "Combustivel": "Gasolina", "CodigoFipe": "057047-8", "MesReferencia": "agosto de 2022 ", "Autenticacao": "rlv1qdhwtqp", "TipoVeiculo": 1, "SiglaCombustivel": "G", "DataConsulta": "terça-feira, 4 de abril de 2023 00:29", "codigoTipoVeiculo": 1, "codigoMesReferencia": 288, "codigoMarca": 34, "codigoModelo": 8576, "codigoTipoCombustivel": 1}, {"Valor": "R$ 338.713,00", "Marca": "Lexus", "Modelo": "ES300h 2.5 16V Aut. (Hybrid)", "AnoModelo": 2022, "Combustivel": "Gasolina", "CodigoFipe": "057047-8", "MesReferencia": "agosto de 2022 ", "Autenticacao": "q4gjh91lwpdmn", "TipoVeiculo": 1, "SiglaCombustivel": "G", "DataConsulta": "terça-feira, 4 de abril de 2023 00:29", "codigoTipoVeiculo": 1, "codigoMesReferencia": 288, "codigoMarca": 34, "codigoModelo": 8576, "codigoTipoCombustivel": 1}, {"Valor": "R$ 329.899,00", "Marca": "Lexus", "Modelo": "ES300h 2.5 16V Aut. (Hybrid)", "AnoModelo": 2021, "Combustivel": "Gasolina", "CodigoFipe": "057047-8", "MesReferencia": "agosto de 2022 ", "Autenticacao": "qs3489gg1jdjf", "TipoVeiculo": 1, "SiglaCombustivel": "G", "DataConsulta": "terça-feira, 4 de abril de 2023 00:29", "codigoTipoVeiculo": 1, "codigoMesReferencia": 288, "codigoMarca": 34, "codigoModelo": 8576, "codigoTipoCombustivel": 1}, {"Valor": "R$ 279.839,00", "Marca": "Lexus", "Modelo": "ES300h 2.5 16V Aut. (Hybrid)", "AnoModelo": 2020, "Combustivel": "Gasolina", "CodigoFipe": "057047-8", "MesReferencia": "agosto de 2022 ", "Autenticacao": "nxfmww6c33dd6", "TipoVeiculo": 1, "SiglaCombustivel": "G", "DataConsulta": "terça-feira, 4 de abril de 2023 00:29", "codigoTipoVeiculo": 1, "codigoMesReferencia": 288, "codigoMarca": 34, "codigoModelo": 8576, "codigoTipoCombustivel": 1}, {"Valor": "R$ 238.940,00", "Marca": "Lexus", "Modelo": "ES300h 2.5 16V Aut. (Hybrid)", "AnoModelo": 2019, "Combustivel": "Gasolina", "CodigoFipe": "057047-8", "MesReferencia": "agosto de 2022 ", "Autenticacao": "mcg2p1fh2yc9z", "TipoVeiculo": 1, "SiglaCombustivel": "G", "DataConsulta": "terça-feira, 4 de abril de 2023 00:29", "codigoTipoVeiculo": 1, "codigoMesReferencia": 288, "codigoMarca": 34, "codigoModelo": 8576, "codigoTipoCombustivel": 1}, {"Valor": "R$ 182.652,00", "Marca": "Lexus", "Modelo": "ES-350 3.5 24V 284cv", "AnoModelo": 2018, "Combustivel": "Gasolina", "CodigoFipe": "057028-1", "MesReferencia": "agosto de 2022 ", "Autenticacao": "j7g5v30hhhc6r", "TipoVeiculo": 1, "SiglaCombustivel": "G", "DataConsulta": "terça-feira, 4 de abril de 2023 00:29", "codigoTipoVeiculo": 1, "codigoMesReferencia": 288, "codigoMarca": 34, "codigoModelo": 4260, "codigoTipoCombustivel": 1}, {"Valor": "R$ 176.697,00", "Marca": "Lexus", "Modelo": "ES-350 3.5 24V 284cv", "AnoModelo": 2017, "Combustivel": "Gasolina", "CodigoFipe": "057028-1", "MesReferencia": "agosto de 2022 ", "Autenticacao": "j0hq1b3g6yc3j", "TipoVeiculo": 1, "SiglaCombustivel": "G", "DataConsulta": "terça-feira, 4 de abril de 2023 00:29", "codigoTipoVeiculo": 1, "codigoMesReferencia": 288, "codigoMarca": 34, "codigoModelo": 4260, "codigoTipoCombustivel": 1}, {"Valor": "R$ 171.756,00", "Marca": "Lexus", "Modelo": "ES-350 3.5 24V 284cv", "AnoModelo": 2016, "Combustivel": "Gasolina", "CodigoFipe": "057028-1", "MesReferencia": "agosto de 2022 ", "Autenticacao": "jtp4q0zsfrcz9", "TipoVeiculo": 1, "SiglaCombustivel": "G", "DataConsulta": "terça-feira, 4 de abril de 2023 00:29", "codigoTipoVeiculo": 1, "codigoMesReferencia": 288, "codigoMarca": 34, "codigoModelo": 4260, "codigoTipoCombustivel": 1}, {"Valor": "R$ 156.204,00", "Marca": "Lexus", "Modelo": "ES-350 3.5 24V 284cv", "AnoModelo": 2015, "Combustivel": "Gasolina", "CodigoFipe": "057028-1", "MesReferencia": "agosto de 2022 ", "Autenticacao": "h7gwfhc0lxcw2", "TipoVeiculo": 1, "SiglaCombustivel": "G", "DataConsulta": "terça-feira, 4 de abril de 2023 00:29", "codigoTipoVeiculo": 1, "codigoMesReferencia": 288, "codigoMarca": 34, "codigoModelo": 4260, "codigoTipoCombustivel": 1}, {"Valor": "R$ 129.409,00", "Marca": "Lexus", "Modelo": "ES-350 3.5 24V 284cv", "AnoModelo": 2014, "Combustivel": "Gasolina", "CodigoFipe": "057028-1", "MesReferencia": "agosto de 2022 ", "Autenticacao": "g61y0bvfn7csv", "TipoVeiculo": 1, "SiglaCombustivel": "G", "DataConsulta": "terça-feira, 4 de abril de 2023 00:29", "codigoTipoVeiculo": 1, "codigoMesReferencia": 288, "codigoMarca": 34, "codigoModelo": 4260, "codigoTipoCombustivel": 1}, {"Valor": "R$ 120.272,00", "Marca": "Lexus", "Modelo": "ES-350 3.5 24V 284cv", "AnoModelo": 2013, "Combustivel": "Gasolina", "CodigoFipe": "057028-1", "MesReferencia": "agosto de 2022 ", "Autenticacao": "gwbvt3vm7ccpm", "TipoVeiculo": 1, "SiglaCombustivel": "G", "DataConsulta": "terça-feira, 4 de abril de 2023 00:29", "codigoTipoVeiculo": 1, "codigoMesReferencia": 288, "codigoMarca": 34, "codigoModelo": 4260, "codigoTipoCombustivel": 1}, {"Valor": "R$ 116.973,00", "Marca": "Lexus", "Modelo": "ES-350 3.5 24V 284cv", "AnoModelo": 2012, "Combustivel": "Gasolina", "CodigoFipe": "057028-1", "MesReferencia": "agosto de 2022 ", "Autenticacao": "grgynxp72ncld", "TipoVeiculo": 1, "SiglaCombustivel": "G", "DataConsulta": "terça-feira, 4 de abril de 2023 00:29", "codigoTipoVeiculo": 1, "codigoMesReferencia": 288, "codigoMarca": 34, "codigoModelo": 4260, "codigoTipoCombustivel": 1}, {"Valor": "R$ 108.020,00", "Marca": "Lexus", "Modelo": "ES-350 3.5 24V 284cv", "AnoModelo": 2011, "Combustivel": "Gasolina", "CodigoFipe": "057028-1", "MesReferencia": "agosto de 2022 ", "Autenticacao": "gdzjtp6f8rcg5", "TipoVeiculo": 1, "SiglaCombustivel": "G", "DataConsulta": "terça-feira, 4 de abril de 2023 00:29", "codigoTipoVeiculo": 1, "codigoMesReferencia": 288, "codigoMarca": 34, "codigoModelo": 4260, "codigoTipoCombustivel": 1}, {"Valor": "R$ 104.682,00", "Marca": "Lexus", "Modelo": "ES-350 3.5 24V 284cv", "AnoModelo": 2010, "Combustivel": "Gasolina", "CodigoFipe": "057028-1", "MesReferencia": "agosto de 2022 ", "Autenticacao": "f816p8cvsxccy", "TipoVeiculo": 1, "SiglaCombustivel": "G", "DataConsulta": "terça-feira, 4 de abril de 2023 00:29", "codigoTipoVeiculo": 1, "codigoMesReferencia": 288, "codigoMarca": 34, "codigoModelo": 4260, "codigoTipoCombustivel": 1}, {"Valor": "R$ 90.943,00", "Marca": "Lexus", "Modelo": "ES-350 3.5 24V 284cv", "AnoModelo": 2009, "Combustivel": "Gasolina", "CodigoFipe": "057028-1", "MesReferencia": "agosto de 2022 ", "Autenticacao": "cfqmf5yrxz58q", "TipoVeiculo": 1, "SiglaCombustivel": "G", "DataConsulta": "terça-feira, 4 de abril de 2023 00:29", "codigoTipoVeiculo": 1, "codigoMesReferencia": 288, "codigoMarca": 34, "codigoModelo": 4260, "codigoTipoCombustivel": 1}, {"Valor": "R$ 70.693,00", "Marca": "Lexus", "Modelo": "ES-350 3.5 24V 284cv", "AnoModelo": 2008, "Combustivel": "Gasolina", "CodigoFipe": "057028-1", "MesReferencia": "agosto de 2022 ", "Autenticacao": "51553vn2t15h", "TipoVeiculo": 1, "SiglaCombustivel": "G", "DataConsulta": "terça-feira, 4 de abril de 2023 00:29", "codigoTipoVeiculo": 1, "codigoMesReferencia": 288, "codigoMarca": 34, "codigoModelo": 4260, "codigoTipoCombustivel": 1}, {"Valor": "R$ 149.434,00", "Marca": "Lexus", "Modelo": "IS-250 2.5 24V 208cv Aut.", "AnoModelo": 2016, "Combustivel": "Gasolina", "CodigoFipe": "057036-2", "MesReferencia": "agosto de 2022 ", "Autenticacao": "hzjs87l29wcz9", "TipoVeiculo": 1, "SiglaCombustivel": "G", "DataConsulta": "terça-feira, 4 de abril de 2023 00:29", "codigoTipoVeiculo": 1, "codigoMesReferencia": 288, "codigoMarca": 34, "codigoModelo": 6537, "codigoTipoCombustivel": 1}, {"Valor": "R$ 131.489,00", "Marca": "Lexus", "Modelo": "IS-250 2.5 24V 208cv Aut.", "AnoModelo": 2015, "Combustivel": "Gasolina", "CodigoFipe": "057036-2", "MesReferencia": "agosto de 2022 ", "Autenticacao": "g9hknkw9cycw2", "TipoVeiculo": 1, "SiglaCombustivel": "G", "DataConsulta": "terça-feira, 4 de abril de 2023 00:29", "codigoTipoVeiculo": 1, "codigoMesReferencia": 288, "codigoMarca": 34, "codigoModelo": 6537, "codigoTipoCombustivel": 1}, {"Valor": "R$ 121.688,00", "Marca": "Lexus", "Modelo": "IS-250 2.5 24V 208cv Aut.", "AnoModelo": 2014, "Combustivel": "Gasolina", "CodigoFipe": "057036-2", "MesReferencia": "agosto de 2022 ", "Autenticacao": "gxz996gvnccsv", "TipoVeiculo": 1, "SiglaCombustivel": "G", "DataConsulta": "terça-feira, 4 de abril de 2023 00:29", "codigoTipoVeiculo": 1, "codigoMesReferencia": 288, "codigoMarca": 34, "codigoModelo": 6537, "codigoTipoCombustivel": 1}, {"Valor": "R$ 126.586,00", "Marca": "Lexus", "Modelo": "IS-250 F Sport 2.5 24V 208cv Aut.", "AnoModelo": 2015, "Combustivel": "Gasolina", "CodigoFipe": "057037-0", "MesReferencia": "agosto de 2022 ", "Autenticacao": "g3rb5knl9lcw2", "TipoVeiculo": 1, "SiglaCombustivel": "G", "DataConsulta": "terça-feira, 4 de abril de 2023 00:29", "codigoTipoVeiculo": 1, "codigoMesReferencia": 288, "codigoMarca": 34, "codigoModelo": 6538, "codigoTipoCombustivel": 1}, {"Valor": "R$ 119.522,00", "Marca": "Lexus", "Modelo": "IS-250 F Sport 2.5 24V 208cv Aut.", "AnoModelo": 2014, "Combustivel": "Gasolina", "CodigoFipe": "057037-0", "MesReferencia": "agosto de 2022 ", "Autenticacao": "gvglr1srjncsv", "TipoVeiculo": 1, "SiglaCombustivel": "G", "DataConsulta": "terça-feira, 4 de abril de 2023 00:29", "codigoTipoVeiculo": 1, "codigoMesReferencia": 288, "codigoMarca": 34, "codigoModelo": 6538, "codigoTipoCombustivel": 1}, {"Valor": "R$ 84.124,00", "Marca": "Lexus", "Modelo": "IS-300 3.0 24V 231cv Aut.", "AnoModelo": 2013, "Combustivel": "Gasolina", "CodigoFipe": "057030-3", "MesReferencia": "agosto de 2022 ", "Autenticacao": "cb4nyp0gg2fnc", "TipoVeiculo": 1, "SiglaCombustivel": "G", "DataConsulta": "terça-feira, 4 de abril de 2023 00:29", "codigoTipoVeiculo": 1, "codigoMesReferencia": 288, "codigoMarca": 34, "codigoModelo": 6066, "codigoTipoCombustivel": 1}, {"Valor": "R$ 81.496,00", "Marca": "Lexus", "Modelo": "IS-300 3.0 24V 231cv Aut.", "AnoModelo": 2012, "Combustivel": "Gasolina", "CodigoFipe": "057030-3", "MesReferencia": "agosto de 2022 ", "Autenticacao": "94vrkh906kj4", "TipoVeiculo": 1, "SiglaCombustivel": "G", "DataConsulta": "terça-feira, 4 de abril de 2023 00:29", "codigoTipoVeiculo": 1, "codigoMesReferencia": 288, "codigoMarca": 34, "codigoModelo": 6066, "codigoTipoCombustivel": 1}, {"Valor": "R$ 340.655,00", "Marca": "Lexus", "Modelo": "LS 460 4.6 32V 347cv", "AnoModelo": 2013, "Combustivel": "Gasolina", "CodigoFipe": "057029-0", "MesReferencia": "agosto de 2022 ", "Autenticacao": "q6q3n78z2tcpm", "TipoVeiculo": 1, "SiglaCombustivel": "G", "DataConsulta": "terça-feira, 4 de abril de 2023 00:29", "codigoTipoVeiculo": 1, "codigoMesReferencia": 288, "codigoMarca": 34, "codigoModelo": 4306, "codigoTipoCombustivel": 1}, {"Valor": "R$ 327.275,00", "Marca": "Lexus", "Modelo": "LS 460 4.6 32V 347cv", "AnoModelo": 2012, "Combustivel": "Gasolina", "CodigoFipe": "057029-0", "MesReferencia": "agosto de 2022 ", "Autenticacao": "qp1spf7ft0cld", "TipoVeiculo": 1, "SiglaCombustivel": "G", "DataConsulta": "terça-feira, 4 de abril de 2023 00:29", "codigoTipoVeiculo": 1, "codigoMesReferencia": 288, "codigoMarca": 34, "codigoModelo": 4306, "codigoTipoCombustivel": 1}, {"Valor": "R$ 310.269,00", "Marca": "Lexus", "Modelo": "LS 460 4.6 32V 347cv", "AnoModelo": 2011, "Combustivel": "Gasolina", "CodigoFipe": "057029-0", "MesReferencia": "agosto de 2022 ", "Autenticacao": "p13n2jc2xqcg5", "TipoVeiculo": 1, "SiglaCombustivel": "G", "DataConsulta": "terça-feira, 4 de abril de 2023 00:29", "codigoTipoVeiculo": 1, "codigoMesReferencia": 288, "codigoMarca": 34, "codigoModelo": 4306, "codigoTipoCombustivel": 1}, {"Valor": "R$ 278.878,00", "Marca": "Lexus", "Modelo": "LS 460 4.6 32V 347cv", "AnoModelo": 2010, "Combustivel": "Gasolina", "CodigoFipe": "057029-0", "MesReferencia": "agosto de 2022 ", "Autenticacao": "nv9p2p0jsxccy", "TipoVeiculo": 1, "SiglaCombustivel": "G", "DataConsulta": "terça-feira, 4 de abril de 2023 00:29", "codigoTipoVeiculo": 1, "codigoMesReferencia": 288, "codigoMarca": 34, "codigoModelo": 4306, "codigoTipoCombustivel": 1}, {"Valor": "R$ 203.674,00", "Marca": "Lexus", "Modelo": "LS 460 4.6 32V 347cv", "AnoModelo": 2009, "Combustivel": "Gasolina", "CodigoFipe": "057029-0", "MesReferencia": "agosto de 2022 ", "Autenticacao": "k038jnht3y8q", "TipoVeiculo": 1, "SiglaCombustivel": "G", "DataConsulta": "terça-feira, 4 de abril de 2023 00:29", "codigoTipoVeiculo": 1, "codigoMesReferencia": 288, "codigoMarca": 34, "codigoModelo": 4306, "codigoTipoCombustivel": 1}, {"Valor": "R$ 180.634,00", "Marca": "Lexus", "Modelo": "LS 460 4.6 32V 347cv", "AnoModelo": 2008, "Combustivel": "Gasolina", "CodigoFipe": "057029-0", "MesReferencia": "agosto de 2022 ", "Autenticacao": "j43t2jkwkb5h", "TipoVeiculo": 1, "SiglaCombustivel": "G", "DataConsulta": "terça-feira, 4 de abril de 2023 00:29", "codigoTipoVeiculo": 1, "codigoMesReferencia": 288, "codigoMarca": 34, "codigoModelo": 4306, "codigoTipoCombustivel": 1}, {"Valor": "R$ 977.449,00", "Marca": "Lexus", "Modelo": "LS 500h 3.5 V6 24v Aut.(Hybrid)", "AnoModelo": 32000, "Combustivel": "Gasolina", "CodigoFipe": "057043-5", "MesReferencia": "agosto de 2022 ", "Autenticacao": "ch9cm2cq83kp", "TipoVeiculo": 1, "SiglaCombustivel": "G", "DataConsulta": "terça-feira, 4 de abril de 2023 00:29", "codigoTipoVeiculo": 1, "codigoMesReferencia": 288, "codigoMarca": 34, "codigoModelo": 8347, "codigoTipoCombustivel": 1}, {"Valor": "R$ 888.925,00", "Marca": "Lexus", "Modelo": "LS 500h 3.5 V6 24v Aut.(Hybrid)", "AnoModelo": 2020, "Combustivel": "Gasolina", "CodigoFipe": "057043-5", "MesReferencia": "agosto de 2022 ", "Autenticacao": "cdyk138x3rcdd6", "TipoVeiculo": 1, "SiglaCombustivel": "G", "DataConsulta": "terça-feira, 4 de abril de 2023 00:29", "codigoTipoVeiculo": 1, "codigoMesReferencia": 288, "codigoMarca": 34, "codigoModelo": 8347, "codigoTipoCombustivel": 1}, {"Valor": "R$ 748.054,00", "Marca": "Lexus", "Modelo": "LS 500h 3.5 V6 24v Aut.(Hybrid)", "AnoModelo": 2019, "Combustivel": "Gasolina", "CodigoFipe": "057043-5", "MesReferencia": "agosto de 2022 ", "Autenticacao": "7mdtw5wdcrc9z", "TipoVeiculo": 1, "SiglaCombustivel": "G", "DataConsulta": "terça-feira, 4 de abril de 2023 00:29", "codigoTipoVeiculo": 1, "codigoMesReferencia": 288, "codigoMarca": 34, "codigoModelo": 8347, "codigoTipoCombustivel": 1}, {"Valor": "R$ 638.520,00", "Marca": "Lexus", "Modelo": "LS 500h 3.5 V6 24v Aut.(Hybrid)", "AnoModelo": 2018, "Combustivel": "Gasolina", "CodigoFipe": "057043-5", "MesReferencia": "agosto de 2022 ", "Autenticacao": "3gzltp97w2c6r", "TipoVeiculo": 1, "SiglaCombustivel": "G", "DataConsulta": "terça-feira, 4 de abril de 2023 00:29", "codigoTipoVeiculo": 1, "codigoMesReferencia": 288, "codigoMarca": 34, "codigoModelo": 8347, "codigoTipoCombustivel": 1}, {"Valor": "R$ 557.280,00", "Marca": "Lexus", "Modelo": "LS-460L 4.6 V8 32v 347cv Aut.", "AnoModelo": 2017, "Combustivel": "Gasolina", "CodigoFipe": "057031-1", "MesReferencia": "agosto de 2022 ", "Autenticacao": "0dqr5lvxvxc3j", "TipoVeiculo": 1, "SiglaCombustivel": "G", "DataConsulta": "terça-feira, 4 de abril de 2023 00:29", "codigoTipoVeiculo": 1, "codigoMesReferencia": 288, "codigoMarca": 34, "codigoModelo": 6067, "codigoTipoCombustivel": 1}, {"Valor": "R$ 503.276,00", "Marca": "Lexus", "Modelo": "LS-460L 4.6 V8 32v 347cv Aut.", "AnoModelo": 2016, "Combustivel": "Gasolina", "CodigoFipe": "057031-1", "MesReferencia": "agosto de 2022 ", "Autenticacao": "ycdwvjf89wcz9", "TipoVeiculo": 1, "SiglaCombustivel": "G", "DataConsulta": "terça-feira, 4 de abril de 2023 00:29", "codigoTipoVeiculo": 1, "codigoMesReferencia": 288, "codigoMarca": 34, "codigoModelo": 6067, "codigoTipoCombustivel": 1}, {"Valor": "R$ 379.557,00", "Marca": "Lexus", "Modelo": "LS-460L 4.6 V8 32v 347cv Aut.", "AnoModelo": 2015, "Combustivel": "Gasolina", "CodigoFipe": "057031-1", "MesReferencia": "agosto de 2022 ", "Autenticacao": "spb2q1vwwxcw2", "TipoVeiculo": 1, "SiglaCombustivel": "G", "DataConsulta": "terça-feira, 4 de abril de 2023 00:29", "codigoTipoVeiculo": 1, "codigoMesReferencia": 288, "codigoMarca": 34, "codigoModelo": 6067, "codigoTipoCombustivel": 1}, {"Valor": "R$ 369.148,00", "Marca": "Lexus", "Modelo": "LS-460L 4.6 V8 32v 347cv Aut.", "AnoModelo": 2014, "Combustivel": "Gasolina", "CodigoFipe": "057031-1", "MesReferencia": "agosto de 2022 ", "Autenticacao": "r84rblg4kjcsv", "TipoVeiculo": 1, "SiglaCombustivel": "G", "DataConsulta": "terça-feira, 4 de abril de 2023 00:29", "codigoTipoVeiculo": 1, "codigoMesReferencia": 288, "codigoMarca": 34, "codigoModelo": 6067, "codigoTipoCombustivel": 1}, {"Valor": "R$ 342.219,00", "Marca": "Lexus", "Modelo": "LS-460L 4.6 V8 32v 347cv Aut.", "AnoModelo": 2013, "Combustivel": "Gasolina", "CodigoFipe": "057031-1", "MesReferencia": "agosto de 2022 ", "Autenticacao": "q8kyxw2s9pcpm", "TipoVeiculo": 1, "SiglaCombustivel": "G", "DataConsulta": "terça-feira, 4 de abril de 2023 00:29", "codigoTipoVeiculo": 1, "codigoMesReferencia": 288, "codigoMarca": 34, "codigoModelo": 6067, "codigoTipoCombustivel": 1}, {"Valor": "R$ 329.865,00", "Marca": "Lexus", "Modelo": "LS-460L 4.6 V8 32v 347cv Aut.", "AnoModelo": 2012, "Combustivel": "Gasolina", "CodigoFipe": "057031-1", "MesReferencia": "agosto de 2022 ", "Autenticacao": "qs2xzpkr8fcld", "TipoVeiculo": 1, "SiglaCombustivel": "G", "DataConsulta": "terça-feira, 4 de abril de 2023 00:29", "codigoTipoVeiculo": 1, "codigoMesReferencia": 288, "codigoMarca": 34, "codigoModelo": 6067, "codigoTipoCombustivel": 1}, {"Valor": "R$ 175.451,00", "Marca": "Lexus", "Modelo": "NX-200t F-Sport 2.0 16v 238cv Aut.", "AnoModelo": 2017, "Combustivel": "Gasolina", "CodigoFipe": "057039-7", "MesReferencia": "agosto de 2022 ", "Autenticacao": "jy1f2841r7c3j", "TipoVeiculo": 1, "SiglaCombustivel": "G", "DataConsulta": "terça-feira, 4 de abril de 2023 00:29", "codigoTipoVeiculo": 1, "codigoMesReferencia": 288, "codigoMarca": 34, "codigoModelo": 7158, "codigoTipoCombustivel": 1}, {"Valor": "R$ 161.958,00", "Marca": "Lexus", "Modelo": "NX-200t F-Sport 2.0 16v 238cv Aut.", "AnoModelo": 2016, "Combustivel": "Gasolina", "CodigoFipe": "057039-7", "MesReferencia": "agosto de 2022 ", "Autenticacao": "jf60sf9mf3cz9", "TipoVeiculo": 1, "SiglaCombustivel": "G", "DataConsulta": "terça-feira, 4 de abril de 2023 00:29", "codigoTipoVeiculo": 1, "codigoMesReferencia": 288, "codigoMarca": 34, "codigoModelo": 7158, "codigoTipoCombustivel": 1}, {"Valor": "R$ 148.941,00", "Marca": "Lexus", "Modelo": "NX-200t F-Sport 2.0 16v 238cv Aut.", "AnoModelo": 2015, "Combustivel": "Gasolina", "CodigoFipe": "057039-7", "MesReferencia": "agosto de 2022 ", "Autenticacao": "hyyws043vncw2", "TipoVeiculo": 1, "SiglaCombustivel": "G", "DataConsulta": "terça-feira, 4 de abril de 2023 00:29", "codigoTipoVeiculo": 1, "codigoMesReferencia": 288, "codigoMarca": 34, "codigoModelo": 7158, "codigoTipoCombustivel": 1}, {"Valor": "R$ 174.514,00", "Marca": "Lexus", "Modelo": "NX-200t Luxury 2.0 16V 238cv Aut.", "AnoModelo": 2017, "Combustivel": "Gasolina", "CodigoFipe": "057038-9", "MesReferencia": "agosto de 2022 ", "Autenticacao": "jxydbdxy9vc3j", "TipoVeiculo": 1, "SiglaCombustivel": "G", "DataConsulta": "terça-feira, 4 de abril de 2023 00:29", "codigoTipoVeiculo": 1, "codigoMesReferencia": 288, "codigoMarca": 34, "codigoModelo": 7159, "codigoTipoCombustivel": 1}, {"Valor": "R$ 157.110,00", "Marca": "Lexus", "Modelo": "NX-200t Luxury 2.0 16V 238cv Aut.", "AnoModelo": 2016, "Combustivel": "Gasolina", "CodigoFipe": "057038-9", "MesReferencia": "agosto de 2022 ", "Autenticacao": "h8js8kq294cz9", "TipoVeiculo": 1, "SiglaCombustivel": "G", "DataConsulta": "terça-feira, 4 de abril de 2023 00:29", "codigoTipoVeiculo": 1, "codigoMesReferencia": 288, "codigoMarca": 34, "codigoModelo": 7159, "codigoTipoCombustivel": 1}, {"Valor": "R$ 143.332,00", "Marca": "Lexus", "Modelo": "NX-200t Luxury 2.0 16V 238cv Aut.", "AnoModelo": 2015, "Combustivel": "Gasolina", "CodigoFipe": "057038-9", "MesReferencia": "agosto de 2022 ", "Autenticacao": "hrc0tvb0zxcw2", "TipoVeiculo": 1, "SiglaCombustivel": "G", "DataConsulta": "terça-feira, 4 de abril de 2023 00:29", "codigoTipoVeiculo": 1, "codigoMesReferencia": 288, "codigoMarca": 34, "codigoModelo": 7159, "codigoTipoCombustivel": 1}, {"Valor": "R$ 187.183,00", "Marca": "Lexus", "Modelo": "NX-300 Dynamic 2.0 16V 238cv Aut.", "AnoModelo": 2018, "Combustivel": "Gasolina", "CodigoFipe": "057042-7", "MesReferencia": "agosto de 2022 ", "Autenticacao": "kdsv6dgl80c6r", "TipoVeiculo": 1, "SiglaCombustivel": "G", "DataConsulta": "terça-feira, 4 de abril de 2023 00:29", "codigoTipoVeiculo": 1, "codigoMesReferencia": 288, "codigoMarca": 34, "codigoModelo": 8179, "codigoTipoCombustivel": 1}, {"Valor": "R$ 198.464,00", "Marca": "Lexus", "Modelo": "NX-300 F-Sport 2.0 16V 238cv Aut.", "AnoModelo": 2018, "Combustivel": "Gasolina", "CodigoFipe": "057040-0", "MesReferencia": "agosto de 2022 ", "Autenticacao": "kt0w398b14c6r", "TipoVeiculo": 1, "SiglaCombustivel": "G", "DataConsulta": "terça-feira, 4 de abril de 2023 00:29", "codigoTipoVeiculo": 1, "codigoMesReferencia": 288, "codigoMarca": 34, "codigoModelo": 8151, "codigoTipoCombustivel": 1}, {"Valor": "R$ 188.255,00", "Marca": "Lexus", "Modelo": "NX-300 Luxury 2.0 16V 238cv Aut.", "AnoModelo": 2018, "Combustivel": "Gasolina", "CodigoFipe": "057041-9", "MesReferencia": "agosto de 2022 ", "Autenticacao": "kf1t2rcm0jc6r", "TipoVeiculo": 1, "SiglaCombustivel": "G", "DataConsulta": "terça-feira, 4 de abril de 2023 00:29", "codigoTipoVeiculo": 1, "codigoMesReferencia": 288, "codigoMarca": 34, "codigoModelo": 8180, "codigoTipoCombustivel": 1}, {"Valor": "R$ 327.417,00", "Marca": "Lexus", "Modelo": "NX-300h Dynamic 2.5 16V Aut.(Hybrid)", "AnoModelo": 32000, "Combustivel": "Gasolina", "CodigoFipe": "057045-1", "MesReferencia": "agosto de 2022 ", "Autenticacao": "qp6ypf1n96p", "TipoVeiculo": 1, "SiglaCombustivel": "G", "DataConsulta": "terça-feira, 4 de abril de 2023 00:29", "codigoTipoVeiculo": 1, "codigoMesReferencia": 288, "codigoMarca": 34, "codigoModelo": 8480, "codigoTipoCombustivel": 1}, {"Valor": "R$ 299.500,00", "Marca": "Lexus", "Modelo": "NX-300h Dynamic 2.5 16V Aut.(Hybrid)", "AnoModelo": 2021, "Combustivel": "Gasolina", "CodigoFipe": "057045-1", "MesReferencia": "agosto de 2022 ", "Autenticacao": "png71gzvf1djf", "TipoVeiculo": 1, "SiglaCombustivel": "G", "DataConsulta": "terça-feira, 4 de abril de 2023 00:29", "codigoTipoVeiculo": 1, "codigoMesReferencia": 288, "codigoMarca": 34, "codigoModelo": 8480, "codigoTipoCombustivel": 1}, {"Valor": "R$ 265.041,00", "Marca": "Lexus", "Modelo": "NX-300h Dynamic 2.5 16V Aut.(Hybrid)", "AnoModelo": 2020, "Combustivel": "Gasolina", "CodigoFipe": "057045-1", "MesReferencia": "agosto de 2022 ", "Autenticacao": "nb2r444kyrdd6", "TipoVeiculo": 1, "SiglaCombustivel": "G", "DataConsulta": "terça-feira, 4 de abril de 2023 00:29", "codigoTipoVeiculo": 1, "codigoMesReferencia": 288, "codigoMarca": 34, "codigoModelo": 8480, "codigoTipoCombustivel": 1}, {"Valor": "R$ 209.067,00", "Marca": "Lexus", "Modelo": "NX-300h Dynamic 2.5 16V Aut.(Hybrid)", "AnoModelo": 2019, "Combustivel": "Gasolina", "CodigoFipe": "057045-1", "MesReferencia": "agosto de 2022 ", "Autenticacao": "k7f83281jyc9z", "TipoVeiculo": 1, "SiglaCombustivel": "G", "DataConsulta": "terça-feira, 4 de abril de 2023 00:29", "codigoTipoVeiculo": 1, "codigoMesReferencia": 288, "codigoMarca": 34, "codigoModelo": 8480, "codigoTipoCombustivel": 1}, {"Valor": "R$ 394.986,00", "Marca": "Lexus", "Modelo": "NX-300h F-Sport 2.5 16V Aut.(Hybrid)", "AnoModelo": 32000, "Combustivel": "Gasolina", "CodigoFipe": "057044-3", "MesReferencia": "agosto de 2022 ", "Autenticacao": "s8fwf8s1lrp", "TipoVeiculo": 1, "SiglaCombustivel": "G", "DataConsulta": "terça-feira, 4 de abril de 2023 00:29", "codigoTipoVeiculo": 1, "codigoMesReferencia": 288, "codigoMarca": 34, "codigoModelo": 8481, "codigoTipoCombustivel": 1}, {"Valor": "R$ 353.996,00", "Marca": "Lexus", "Modelo": "NX-300h F-Sport 2.5 16V Aut.(Hybrid)", "AnoModelo": 2021, "Combustivel": "Gasolina", "CodigoFipe": "057044-3", "MesReferencia": "agosto de 2022 ", "Autenticacao": "rqc0qt3cf7djf", "TipoVeiculo": 1, "SiglaCombustivel": "G", "DataConsulta": "terça-feira, 4 de abril de 2023 00:29", "codigoTipoVeiculo": 1, "codigoMesReferencia": 288, "codigoMarca": 34, "codigoModelo": 8481, "codigoTipoCombustivel": 1}, {"Valor": "R$ 296.455,00", "Marca": "Lexus", "Modelo": "NX-300h F-Sport 2.5 16V Aut.(Hybrid)", "AnoModelo": 2020, "Combustivel": "Gasolina", "CodigoFipe": "057044-3", "MesReferencia": "agosto de 2022 ", "Autenticacao": "pjxk2b6cwndd6", "TipoVeiculo": 1, "SiglaCombustivel": "G", "DataConsulta": "terça-feira, 4 de abril de 2023 00:29", "codigoTipoVeiculo": 1, "codigoMesReferencia": 288, "codigoMarca": 34, "codigoModelo": 8481, "codigoTipoCombustivel": 1}, {"Valor": "R$ 239.779,00", "Marca": "Lexus", "Modelo": "NX-300h F-Sport 2.5 16V Aut.(Hybrid)", "AnoModelo": 2019, "Combustivel": "Gasolina", "CodigoFipe": "057044-3", "MesReferencia": "agosto de 2022 ", "Autenticacao": "mdgk1t05ljc9z", "TipoVeiculo": 1, "SiglaCombustivel": "G", "DataConsulta": "terça-feira, 4 de abril de 2023 00:29", "codigoTipoVeiculo": 1, "codigoMesReferencia": 288, "codigoMarca": 34, "codigoModelo": 8481, "codigoTipoCombustivel": 1}, {"Valor": "R$ 339.132,00", "Marca": "Lexus", "Modelo": "NX-300h Luxury 2.5 16V Aut.(Hybrid)", "AnoModelo": 32000, "Combustivel": "Gasolina", "CodigoFipe": "057046-0", "MesReferencia": "agosto de 2022 ", "Autenticacao": "q4yrmrfpf3p", "TipoVeiculo": 1, "SiglaCombustivel": "G", "DataConsulta": "terça-feira, 4 de abril de 2023 00:29", "codigoTipoVeiculo": 1, "codigoMesReferencia": 288, "codigoMarca": 34, "codigoModelo": 8482, "codigoTipoCombustivel": 1}, {"Valor": "R$ 326.311,00", "Marca": "Lexus", "Modelo": "NX-300h Luxury 2.5 16V Aut.(Hybrid)", "AnoModelo": 2021, "Combustivel": "Gasolina", "CodigoFipe": "057046-0", "MesReferencia": "agosto de 2022 ", "Autenticacao": "qnxrhhjc6fdjf", "TipoVeiculo": 1, "SiglaCombustivel": "G", "DataConsulta": "terça-feira, 4 de abril de 2023 00:29", "codigoTipoVeiculo": 1, "codigoMesReferencia": 288, "codigoMarca": 34, "codigoModelo": 8482, "codigoTipoCombustivel": 1}, {"Valor": "R$ 285.892,00", "Marca": "Lexus", "Modelo": "NX-300h Luxury 2.5 16V Aut.(Hybrid)", "AnoModelo": 2020, "Combustivel": "Gasolina", "CodigoFipe": "057046-0", "MesReferencia": "agosto de 2022 ", "Autenticacao": "n4jm4rp5s0dd6", "TipoVeiculo": 1, "SiglaCombustivel": "G", "DataConsulta": "terça-feira, 4 de abril de 2023 00:29", "codigoTipoVeiculo": 1, "codigoMesReferencia": 288, "codigoMarca": 34, "codigoModelo": 8482, "codigoTipoCombustivel": 1}, {"Valor": "R$ 227.651,00", "Marca": "Lexus", "Modelo": "NX-300h Luxury 2.5 16V Aut.(Hybrid)", "AnoModelo": 2019, "Combustivel": "Gasolina", "CodigoFipe": "057046-0", "MesReferencia": "agosto de 2022 ", "Autenticacao": "lx7rrn3ws4c9z", "TipoVeiculo": 1, "SiglaCombustivel": "G", "DataConsulta": "terça-feira, 4 de abril de 2023 00:29", "codigoTipoVeiculo": 1, "codigoMesReferencia": 288, "codigoMarca": 34, "codigoModelo": 8482, "codigoTipoCombustivel": 1}, {"Valor": "R$ 353.909,00", "Marca": "Lexus", "Modelo": "NX-350h Dynamic 2.5 16V Aut. (Hybrid)", "AnoModelo": 32000, "Combustivel": "Gasolina", "CodigoFipe": "057054-0", "MesReferencia": "agosto de 2022 ", "Autenticacao": "rp8vpzklzwp", "TipoVeiculo": 1, "SiglaCombustivel": "G", "DataConsulta": "terça-feira, 4 de abril de 2023 00:29", "codigoTipoVeiculo": 1, "codigoMesReferencia": 288, "codigoMarca": 34, "codigoModelo": 9766, "codigoTipoCombustivel": 1}, {"Valor": "R$ 330.005,00", "Marca": "Lexus", "Modelo": "NX-350h Dynamic 2.5 16V Aut. (Hybrid)", "AnoModelo": 2022, "Combustivel": "Gasolina", "CodigoFipe": "057054-0", "MesReferencia": "agosto de 2022 ", "Autenticacao": "qs70qtp1vydmn", "TipoVeiculo": 1, "SiglaCombustivel": "G", "DataConsulta": "terça-feira, 4 de abril de 2023 00:29", "codigoTipoVeiculo": 1, "codigoMesReferencia": 288, "codigoMarca": 34, "codigoModelo": 9766, "codigoTipoCombustivel": 1}, {"Valor": "R$ 425.909,00", "Marca": "Lexus", "Modelo": "NX-350h F-Sport 2.5 16V Aut. (Hybrid)", "AnoModelo": 32000, "Combustivel": "Gasolina", "CodigoFipe": "057055-9", "MesReferencia": "agosto de 2022 ", "Autenticacao": "vfpt333gmdp", "TipoVeiculo": 1, "SiglaCombustivel": "G", "DataConsulta": "terça-feira, 4 de abril de 2023 00:29", "codigoTipoVeiculo": 1, "codigoMesReferencia": 288, "codigoMarca": 34, "codigoModelo": 9767, "codigoTipoCombustivel": 1}, {"Valor": "R$ 395.982,00", "Marca": "Lexus", "Modelo": "NX-350h F-Sport 2.5 16V Aut. (Hybrid)", "AnoModelo": 2022, "Combustivel": "Gasolina", "CodigoFipe": "057055-9", "MesReferencia": "agosto de 2022 ", "Autenticacao": "s9l2pz3bttdmn", "TipoVeiculo": 1, "SiglaCombustivel": "G", "DataConsulta": "terça-feira, 4 de abril de 2023 00:29", "codigoTipoVeiculo": 1, "codigoMesReferencia": 288, "codigoMarca": 34, "codigoModelo": 9767, "codigoTipoCombustivel": 1}, {"Valor": "R$ 391.054,00", "Marca": "Lexus", "Modelo": "NX-350h Luxury 2.5 16V Aut. (Hybrid)", "AnoModelo": 32000, "Combustivel": "Gasolina", "CodigoFipe": "057053-2", "MesReferencia": "agosto de 2022 ", "Autenticacao": "s3ty1rj1lyp", "TipoVeiculo": 1, "SiglaCombustivel": "G", "DataConsulta": "terça-feira, 4 de abril de 2023 00:29", "codigoTipoVeiculo": 1, "codigoMesReferencia": 288, "codigoMarca": 34, "codigoModelo": 9768, "codigoTipoCombustivel": 1}, {"Valor": "R$ 364.231,00", "Marca": "Lexus", "Modelo": "NX-350h Luxury 2.5 16V Aut. (Hybrid)", "AnoModelo": 2022, "Combustivel": "Gasolina", "CodigoFipe": "057053-2", "MesReferencia": "agosto de 2022 ", "Autenticacao": "r3c02k79bfdmn", "TipoVeiculo": 1, "SiglaCombustivel": "G", "DataConsulta": "terça-feira, 4 de abril de 2023 00:29", "codigoTipoVeiculo": 1, "codigoMesReferencia": 288, "codigoMarca": 34, "codigoModelo": 9768, "codigoTipoCombustivel": 1}, {"Valor": "R$ 412.430,00", "Marca": "Lexus", "Modelo": "RX-350 3.5 24V  Aut.", "AnoModelo": 2019, "Combustivel": "Gasolina", "CodigoFipe": "057032-0", "MesReferencia": "agosto de 2022 ", "Autenticacao": "txwxk866jvc9z", "TipoVeiculo": 1, "SiglaCombustivel": "G", "DataConsulta": "terça-feira, 4 de abril de 2023 00:29", "codigoTipoVeiculo": 1, "codigoMesReferencia": 288, "codigoMarca": 34, "codigoModelo": 6068, "codigoTipoCombustivel": 1}, {"Valor": "R$ 302.060,00", "Marca": "Lexus", "Modelo": "RX-350 3.5 24V  Aut.", "AnoModelo": 2018, "Combustivel": "Gasolina", "CodigoFipe": "057032-0", "MesReferencia": "agosto de 2022 ", "Autenticacao": "prg9jthmvpc6r", "TipoVeiculo": 1, "SiglaCombustivel": "G", "DataConsulta": "terça-feira, 4 de abril de 2023 00:29", "codigoTipoVeiculo": 1, "codigoMesReferencia": 288, "codigoMarca": 34, "codigoModelo": 6068, "codigoTipoCombustivel": 1}, {"Valor": "R$ 268.949,00", "Marca": "Lexus", "Modelo": "RX-350 3.5 24V  Aut.", "AnoModelo": 2017, "Combustivel": "Gasolina", "CodigoFipe": "057032-0", "MesReferencia": "agosto de 2022 ", "Autenticacao": "nhntjcscf4c3j", "TipoVeiculo": 1, "SiglaCombustivel": "G", "DataConsulta": "terça-feira, 4 de abril de 2023 00:29", "codigoTipoVeiculo": 1, "codigoMesReferencia": 288, "codigoMarca": 34, "codigoModelo": 6068, "codigoTipoCombustivel": 1}, {"Valor": "R$ 212.596,00", "Marca": "Lexus", "Modelo": "RX-350 3.5 24V  Aut.", "AnoModelo": 2016, "Combustivel": "Gasolina", "CodigoFipe": "057032-0", "MesReferencia": "agosto de 2022 ", "Autenticacao": "lclkf10trqcz9", "TipoVeiculo": 1, "SiglaCombustivel": "G", "DataConsulta": "terça-feira, 4 de abril de 2023 00:29", "codigoTipoVeiculo": 1, "codigoMesReferencia": 288, "codigoMarca": 34, "codigoModelo": 6068, "codigoTipoCombustivel": 1}, {"Valor": "R$ 163.238,00", "Marca": "Lexus", "Modelo": "RX-350 3.5 24V  Aut.", "AnoModelo": 2015, "Combustivel": "Gasolina", "CodigoFipe": "057032-0", "MesReferencia": "agosto de 2022 ", "Autenticacao": "jhqj032dqmcw2", "TipoVeiculo": 1, "SiglaCombustivel": "G", "DataConsulta": "terça-feira, 4 de abril de 2023 00:29", "codigoTipoVeiculo": 1, "codigoMesReferencia": 288, "codigoMarca": 34, "codigoModelo": 6068, "codigoTipoCombustivel": 1}, {"Valor": "R$ 133.413,00", "Marca": "Lexus", "Modelo": "RX-350 3.5 24V  Aut.", "AnoModelo": 2014, "Combustivel": "Gasolina", "CodigoFipe": "057032-0", "MesReferencia": "agosto de 2022 ", "Autenticacao": "hcrhjsx302csv", "TipoVeiculo": 1, "SiglaCombustivel": "G", "DataConsulta": "terça-feira, 4 de abril de 2023 00:29", "codigoTipoVeiculo": 1, "codigoMesReferencia": 288, "codigoMarca": 34, "codigoModelo": 6068, "codigoTipoCombustivel": 1}, {"Valor": "R$ 129.753,00", "Marca": "Lexus", "Modelo": "RX-350 3.5 24V  Aut.", "AnoModelo": 2013, "Combustivel": "Gasolina", "CodigoFipe": "057032-0", "MesReferencia": "agosto de 2022 ", "Autenticacao": "g7ggl2h1n1cpm", "TipoVeiculo": 1, "SiglaCombustivel": "G", "DataConsulta": "terça-feira, 4 de abril de 2023 00:29", "codigoTipoVeiculo": 1, "codigoMesReferencia": 288, "codigoMarca": 34, "codigoModelo": 6068, "codigoTipoCombustivel": 1}, {"Valor": "R$ 412.430,00", "Marca": "Lexus", "Modelo": "RX-350 F-Sport 3.5 24V Aut.", "AnoModelo": 2019, "Combustivel": "Gasolina", "CodigoFipe": "057033-8", "MesReferencia": "agosto de 2022 ", "Autenticacao": "txwxk87zk0c9z", "TipoVeiculo": 1, "SiglaCombustivel": "G", "DataConsulta": "terça-feira, 4 de abril de 2023 00:29", "codigoTipoVeiculo": 1, "codigoMesReferencia": 288, "codigoMarca": 34, "codigoModelo": 6299, "codigoTipoCombustivel": 1}, {"Valor": "R$ 305.702,00", "Marca": "Lexus", "Modelo": "RX-350 F-Sport 3.5 24V Aut.", "AnoModelo": 2018, "Combustivel": "Gasolina", "CodigoFipe": "057033-8", "MesReferencia": "agosto de 2022 ", "Autenticacao": "pwrn5s945lc6r", "TipoVeiculo": 1, "SiglaCombustivel": "G", "DataConsulta": "terça-feira, 4 de abril de 2023 00:29", "codigoTipoVeiculo": 1, "codigoMesReferencia": 288, "codigoMarca": 34, "codigoModelo": 6299, "codigoTipoCombustivel": 1}, {"Valor": "R$ 269.286,00", "Marca": "Lexus", "Modelo": "RX-350 F-Sport 3.5 24V Aut.", "AnoModelo": 2017, "Combustivel": "Gasolina", "CodigoFipe": "057033-8", "MesReferencia": "agosto de 2022 ", "Autenticacao": "nh117llc77c3j", "TipoVeiculo": 1, "SiglaCombustivel": "G", "DataConsulta": "terça-feira, 4 de abril de 2023 00:29", "codigoTipoVeiculo": 1, "codigoMesReferencia": 288, "codigoMarca": 34, "codigoModelo": 6299, "codigoTipoCombustivel": 1}, {"Valor": "R$ 224.135,00", "Marca": "Lexus", "Modelo": "RX-350 F-Sport 3.5 24V Aut.", "AnoModelo": 2016, "Combustivel": "Gasolina", "CodigoFipe": "057033-8", "MesReferencia": "agosto de 2022 ", "Autenticacao": "ls3y2sf2whcz9", "TipoVeiculo": 1, "SiglaCombustivel": "G", "DataConsulta": "terça-feira, 4 de abril de 2023 00:29", "codigoTipoVeiculo": 1, "codigoMesReferencia": 288, "codigoMarca": 34, "codigoModelo": 6299, "codigoTipoCombustivel": 1}, {"Valor": "R$ 172.422,00", "Marca": "Lexus", "Modelo": "RX-350 F-Sport 3.5 24V Aut.", "AnoModelo": 2015, "Combustivel": "Gasolina", "CodigoFipe": "057033-8", "MesReferencia": "agosto de 2022 ", "Autenticacao": "jvhb408nbxcw2", "TipoVeiculo": 1, "SiglaCombustivel": "G", "DataConsulta": "terça-feira, 4 de abril de 2023 00:29", "codigoTipoVeiculo": 1, "codigoMesReferencia": 288, "codigoMarca": 34, "codigoModelo": 6299, "codigoTipoCombustivel": 1}, {"Valor": "R$ 136.856,00", "Marca": "Lexus", "Modelo": "RX-350 F-Sport 3.5 24V Aut.", "AnoModelo": 2014, "Combustivel": "Gasolina", "CodigoFipe": "057033-8", "MesReferencia": "agosto de 2022 ", "Autenticacao": "hhsmyt2ws8csv", "TipoVeiculo": 1, "SiglaCombustivel": "G", "DataConsulta": "terça-feira, 4 de abril de 2023 00:29", "codigoTipoVeiculo": 1, "codigoMesReferencia": 288, "codigoMarca": 34, "codigoModelo": 6299, "codigoTipoCombustivel": 1}, {"Valor": "R$ 132.033,00", "Marca": "Lexus", "Modelo": "RX-350 F-Sport 3.5 24V Aut.", "AnoModelo": 2013, "Combustivel": "Gasolina", "CodigoFipe": "057033-8", "MesReferencia": "agosto de 2022 ", "Autenticacao": "g94bl5tzqzcpm", "TipoVeiculo": 1, "SiglaCombustivel": "G", "DataConsulta": "terça-feira, 4 de abril de 2023 00:29", "codigoTipoVeiculo": 1, "codigoMesReferencia": 288, "codigoMarca": 34, "codigoModelo": 6299, "codigoTipoCombustivel": 1}, {"Valor": "R$ 527.104,00", "Marca": "Lexus", "Modelo": "RX-450h F-Sport 3.5 24V V6 Aut.(Hybrid)", "AnoModelo": 32000, "Combustivel": "Gasolina", "CodigoFipe": "057052-4", "MesReferencia": "agosto de 2022 ", "Autenticacao": "y8by51wt12p", "TipoVeiculo": 1, "SiglaCombustivel": "G", "DataConsulta": "terça-feira, 4 de abril de 2023 00:29", "codigoTipoVeiculo": 1, "codigoMesReferencia": 288, "codigoMarca": 34, "codigoModelo": 9054, "codigoTipoCombustivel": 1}, {"Valor": "R$ 490.494,00", "Marca": "Lexus", "Modelo": "RX-450h F-Sport 3.5 24V V6 Aut.(Hybrid)", "AnoModelo": 2022, "Combustivel": "Gasolina", "CodigoFipe": "057052-4", "MesReferencia": "agosto de 2022 ", "Autenticacao": "xwd9njj666dmn", "TipoVeiculo": 1, "SiglaCombustivel": "G", "DataConsulta": "terça-feira, 4 de abril de 2023 00:29", "codigoTipoVeiculo": 1, "codigoMesReferencia": 288, "codigoMarca": 34, "codigoModelo": 9054, "codigoTipoCombustivel": 1}, {"Valor": "R$ 478.231,00", "Marca": "Lexus", "Modelo": "RX-450h F-Sport 3.5 24V V6 Aut.(Hybrid)", "AnoModelo": 2021, "Combustivel": "Gasolina", "CodigoFipe": "057052-4", "MesReferencia": "agosto de 2022 ", "Autenticacao": "xd1k7wyz8xdjf", "TipoVeiculo": 1, "SiglaCombustivel": "G", "DataConsulta": "terça-feira, 4 de abril de 2023 00:29", "codigoTipoVeiculo": 1, "codigoMesReferencia": 288, "codigoMarca": 34, "codigoModelo": 9054, "codigoTipoCombustivel": 1}, {"Valor": "R$ 418.645,00", "Marca": "Lexus", "Modelo": "RX-450h F-Sport 3.5 24V V6 Aut.(Hybrid)", "AnoModelo": 2020, "Combustivel": "Gasolina", "CodigoFipe": "057052-4", "MesReferencia": "agosto de 2022 ", "Autenticacao": "t45tcqn8cvdd6", "TipoVeiculo": 1, "SiglaCombustivel": "G", "DataConsulta": "terça-feira, 4 de abril de 2023 00:29", "codigoTipoVeiculo": 1, "codigoMesReferencia": 288, "codigoMarca": 34, "codigoModelo": 9054, "codigoTipoCombustivel": 1}, {"Valor": "R$ 516.329,00", "Marca": "Lexus", "Modelo": "RX-450h Luxury 3.5 24V V6 Aut.(Hybrid)", "AnoModelo": 32000, "Combustivel": "Gasolina", "CodigoFipe": "057051-6", "MesReferencia": "agosto de 2022 ", "Autenticacao": "yvqbdd5gz0p", "TipoVeiculo": 1, "SiglaCombustivel": "G", "DataConsulta": "terça-feira, 4 de abril de 2023 00:29", "codigoTipoVeiculo": 1, "codigoMesReferencia": 288, "codigoMarca": 34, "codigoModelo": 9055, "codigoTipoCombustivel": 1}, {"Valor": "R$ 466.450,00", "Marca": "Lexus", "Modelo": "RX-450h Luxury 3.5 24V V6 Aut.(Hybrid)", "AnoModelo": 2022, "Combustivel": "Gasolina", "CodigoFipe": "057051-6", "MesReferencia": "agosto de 2022 ", "Autenticacao": "wy7cx7ytjmdmn", "TipoVeiculo": 1, "SiglaCombustivel": "G", "DataConsulta": "terça-feira, 4 de abril de 2023 00:29", "codigoTipoVeiculo": 1, "codigoMesReferencia": 288, "codigoMarca": 34, "codigoModelo": 9055, "codigoTipoCombustivel": 1}, {"Valor": "R$ 445.977,00", "Marca": "Lexus", "Modelo": "RX-450h Luxury 3.5 24V V6 Aut.(Hybrid)", "AnoModelo": 2021, "Combustivel": "Gasolina", "CodigoFipe": "057051-6", "MesReferencia": "agosto de 2022 ", "Autenticacao": "v567vzg1fxdjf", "TipoVeiculo": 1, "SiglaCombustivel": "G", "DataConsulta": "terça-feira, 4 de abril de 2023 00:29", "codigoTipoVeiculo": 1, "codigoMesReferencia": 288, "codigoMarca": 34, "codigoModelo": 9055, "codigoTipoCombustivel": 1}, {"Valor": "R$ 415.349,00", "Marca": "Lexus", "Modelo": "RX-450h Luxury 3.5 24V V6 Aut.(Hybrid)", "AnoModelo": 2020, "Combustivel": "Gasolina", "CodigoFipe": "057051-6", "MesReferencia": "agosto de 2022 ", "Autenticacao": "t090k9zfhxdd6", "TipoVeiculo": 1, "SiglaCombustivel": "G", "DataConsulta": "terça-feira, 4 de abril de 2023 00:29", "codigoTipoVeiculo": 1, "codigoMesReferencia": 288, "codigoMarca": 34, "codigoModelo": 9055, "codigoTipoCombustivel": 1}, {"Valor": "R$ 281.667,00", "Marca": "Lexus", "Modelo": "UX-250h Dynamic 2.0 16V Aut.(Hybrid)", "AnoModelo": 32000, "Combustivel": "Gasolina", "CodigoFipe": "057050-8", "MesReferencia": "agosto de 2022 ", "Autenticacao": "nzk2lw9gb2p", "TipoVeiculo": 1, "SiglaCombustivel": "G", "DataConsulta": "terça-feira, 4 de abril de 2023 00:29", "codigoTipoVeiculo": 1, "codigoMesReferencia": 288, "codigoMarca": 34, "codigoModelo": 8696, "codigoTipoCombustivel": 1}, {"Valor": "R$ 264.963,00", "Marca": "Lexus", "Modelo": "UX-250h Dynamic 2.0 16V Aut.(Hybrid)", "AnoModelo": 2022, "Combustivel": "Gasolina", "CodigoFipe": "057050-8", "MesReferencia": "agosto de 2022 ", "Autenticacao": "nbzx8nswr8dmn", "TipoVeiculo": 1, "SiglaCombustivel": "G", "DataConsulta": "terça-feira, 4 de abril de 2023 00:29", "codigoTipoVeiculo": 1, "codigoMesReferencia": 288, "codigoMarca": 34, "codigoModelo": 8696, "codigoTipoCombustivel": 1}, {"Valor": "R$ 240.540,00", "Marca": "Lexus", "Modelo": "UX-250h Dynamic 2.0 16V Aut.(Hybrid)", "AnoModelo": 2021, "Combustivel": "Gasolina", "CodigoFipe": "057050-8", "MesReferencia": "agosto de 2022 ", "Autenticacao": "mfb7h39gpvdjf", "TipoVeiculo": 1, "SiglaCombustivel": "G", "DataConsulta": "terça-feira, 4 de abril de 2023 00:29", "codigoTipoVeiculo": 1, "codigoMesReferencia": 288, "codigoMarca": 34, "codigoModelo": 8696, "codigoTipoCombustivel": 1}, {"Valor": "R$ 210.621,00", "Marca": "Lexus", "Modelo": "UX-250h Dynamic 2.0 16V Aut.(Hybrid)", "AnoModelo": 2020, "Combustivel": "Gasolina", "CodigoFipe": "057050-8", "MesReferencia": "agosto de 2022 ", "Autenticacao": "k88r3fstqsdd6", "TipoVeiculo": 1, "SiglaCombustivel": "G", "DataConsulta": "terça-feira, 4 de abril de 2023 00:29", "codigoTipoVeiculo": 1, "codigoMesReferencia": 288, "codigoMarca": 34, "codigoModelo": 8696, "codigoTipoCombustivel": 1}, {"Valor": "R$ 182.587,00", "Marca": "Lexus", "Modelo": "UX-250h Dynamic 2.0 16V Aut.(Hybrid)", "AnoModelo": 2019, "Combustivel": "Gasolina", "CodigoFipe": "057050-8", "MesReferencia": "agosto de 2022 ", "Autenticacao": "j7dtmqpcwmc9z", "TipoVeiculo": 1, "SiglaCombustivel": "G", "DataConsulta": "terça-feira, 4 de abril de 2023 00:29", "codigoTipoVeiculo": 1, "codigoMesReferencia": 288, "codigoMarca": 34, "codigoModelo": 8696, "codigoTipoCombustivel": 1}, {"Valor": "R$ 287.149,00", "Marca": "Lexus", "Modelo": "UX-250h F-Sport 2.0 16V Aut.(Hybrid)", "AnoModelo": 2020, "Combustivel": "Gasolina", "CodigoFipe": "057048-6", "MesReferencia": "agosto de 2022 ", "Autenticacao": "n50bg1x25bdd6", "TipoVeiculo": 1, "SiglaCombustivel": "G", "DataConsulta": "terça-feira, 4 de abril de 2023 00:29", "codigoTipoVeiculo": 1, "codigoMesReferencia": 288, "codigoMarca": 34, "codigoModelo": 8697, "codigoTipoCombustivel": 1}, {"Valor": "R$ 198.875,00", "Marca": "Lexus", "Modelo": "UX-250h F-Sport 2.0 16V Aut.(Hybrid)", "AnoModelo": 2019, "Combustivel": "Gasolina", "CodigoFipe": "057048-6", "MesReferencia": "agosto de 2022 ", "Autenticacao": "kvht6963dkc9z", "TipoVeiculo": 1, "SiglaCombustivel": "G", "DataConsulta": "terça-feira, 4 de abril de 2023 00:29", "codigoTipoVeiculo": 1, "codigoMesReferencia": 288, "codigoMarca": 34, "codigoModelo": 8697, "codigoTipoCombustivel": 1}, {"Valor": "R$ 303.766,00", "Marca": "Lexus", "Modelo": "UX-250h Luxury 2.0 16V Aut.(Hybrid)", "AnoModelo": 32000, "Combustivel": "Gasolina", "CodigoFipe": "057049-4", "MesReferencia": "agosto de 2022 ", "Autenticacao": "ptg9sfrlngp", "TipoVeiculo": 1, "SiglaCombustivel": "G", "DataConsulta": "terça-feira, 4 de abril de 2023 00:29", "codigoTipoVeiculo": 1, "codigoMesReferencia": 288, "codigoMarca": 34, "codigoModelo": 8698, "codigoTipoCombustivel": 1}, {"Valor": "R$ 285.260,00", "Marca": "Lexus", "Modelo": "UX-250h Luxury 2.0 16V Aut.(Hybrid)", "AnoModelo": 2022, "Combustivel": "Gasolina", "CodigoFipe": "057049-4", "MesReferencia": "agosto de 2022 ", "Autenticacao": "n3sn1b847ldmn", "TipoVeiculo": 1, "SiglaCombustivel": "G", "DataConsulta": "terça-feira, 4 de abril de 2023 00:29", "codigoTipoVeiculo": 1, "codigoMesReferencia": 288, "codigoMarca": 34, "codigoModelo": 8698, "codigoTipoCombustivel": 1}, {"Valor": "R$ 271.382,00", "Marca": "Lexus", "Modelo": "UX-250h Luxury 2.0 16V Aut.(Hybrid)", "AnoModelo": 2021, "Combustivel": "Gasolina", "CodigoFipe": "057049-4", "MesReferencia": "agosto de 2022 ", "Autenticacao": "nlh7xpnl8rdjf", "TipoVeiculo": 1, "SiglaCombustivel": "G", "DataConsulta": "terça-feira, 4 de abril de 2023 00:29", "codigoTipoVeiculo": 1, "codigoMesReferencia": 288, "codigoMarca": 34, "codigoModelo": 8698, "codigoTipoCombustivel": 1}, {"Valor": "R$ 241.757,00", "Marca": "Lexus", "Modelo": "UX-250h Luxury 2.0 16V Aut.(Hybrid)", "AnoModelo": 2020, "Combustivel": "Gasolina", "CodigoFipe": "057049-4", "MesReferencia": "agosto de 2022 ", "Autenticacao": "mgsgr7z8vfdd6", "TipoVeiculo": 1, "SiglaCombustivel": "G", "DataConsulta": "terça-feira, 4 de abril de 2023 00:29", "codigoTipoVeiculo": 1, "codigoMesReferencia": 288, "codigoMarca": 34, "codigoModelo": 8698, "codigoTipoCombustivel": 1}, {"Valor": "R$ 192.062,00", "Marca": "Lexus", "Modelo": "UX-250h Luxury 2.0 16V Aut.(Hybrid)", "AnoModelo": 2019, "Combustivel": "Gasolina", "CodigoFipe": "057049-4", "MesReferencia": "agosto de 2022 ", "Autenticacao": "klh6m28l1dc9z", "TipoVeiculo": 1, "SiglaCombustivel": "G", "DataConsulta": "terça-feira, 4 de abril de 2023 00:29", "codigoTipoVeiculo": 1, "codigoMesReferencia": 288, "codigoMarca": 34, "codigoModelo": 8698, "codigoTipoCombustivel": 1}]