[{"Valor": "R$ 98.800,00", "Marca": "Fibravan", "Modelo": "Buggy Off Road 1.8 8V", "AnoModelo": 32000, "Combustivel": "Gasolina", "CodigoFipe": "067004-9", "MesReferencia": "agosto de 2022 ", "Autenticacao": "cjpq7dhjj5wp", "TipoVeiculo": 1, "SiglaCombustivel": "G", "DataConsulta": "terça-feira, 4 de abril de 2023 00:15", "codigoTipoVeiculo": 1, "codigoMesReferencia": 288, "codigoMarca": 149, "codigoModelo": 4890, "codigoTipoCombustivel": 1}, {"Valor": "R$ 90.402,00", "Marca": "Fibravan", "Modelo": "Buggy Off Road 1.8 8V", "AnoModelo": 2023, "Combustivel": "Gasolina", "CodigoFipe": "067004-9", "MesReferencia": "agosto de 2022 ", "Autenticacao": "cfh8tfq9q4knc", "TipoVeiculo": 1, "SiglaCombustivel": "G", "DataConsulta": "terça-feira, 4 de abril de 2023 00:15", "codigoTipoVeiculo": 1, "codigoMesReferencia": 288, "codigoMarca": 149, "codigoModelo": 4890, "codigoTipoCombustivel": 1}, {"Valor": "R$ 86.914,00", "Marca": "Fibravan", "Modelo": "Buggy Off Road 1.8 8V", "AnoModelo": 2022, "Combustivel": "Gasolina", "CodigoFipe": "067004-9", "MesReferencia": "agosto de 2022 ", "Autenticacao": "cc6c054fpvzj4", "TipoVeiculo": 1, "SiglaCombustivel": "G", "DataConsulta": "terça-feira, 4 de abril de 2023 00:15", "codigoTipoVeiculo": 1, "codigoMesReferencia": 288, "codigoMarca": 149, "codigoModelo": 4890, "codigoTipoCombustivel": 1}, {"Valor": "R$ 78.823,00", "Marca": "Fibravan", "Modelo": "Buggy Off Road 1.8 8V", "AnoModelo": 2021, "Combustivel": "Gasolina", "CodigoFipe": "067004-9", "MesReferencia": "agosto de 2022 ", "Autenticacao": "84h6cq9zrzfx", "TipoVeiculo": 1, "SiglaCombustivel": "G", "DataConsulta": "terça-feira, 4 de abril de 2023 00:15", "codigoTipoVeiculo": 1, "codigoMesReferencia": 288, "codigoMarca": 149, "codigoModelo": 4890, "codigoTipoCombustivel": 1}, {"Valor": "R$ 57.925,00", "Marca": "Fibravan", "Modelo": "Buggy Off Road 1.8 8V", "AnoModelo": 2020, "Combustivel": "Gasolina", "CodigoFipe": "067004-9", "MesReferencia": "agosto de 2022 ", "Autenticacao": "07hdxxs40bp", "TipoVeiculo": 1, "SiglaCombustivel": "G", "DataConsulta": "terça-feira, 4 de abril de 2023 00:15", "codigoTipoVeiculo": 1, "codigoMesReferencia": 288, "codigoMarca": 149, "codigoModelo": 4890, "codigoTipoCombustivel": 1}, {"Valor": "R$ 49.733,00", "Marca": "Fibravan", "Modelo": "Buggy Off Road 1.8 8V", "AnoModelo": 2019, "Combustivel": "Gasolina", "CodigoFipe": "067004-9", "MesReferencia": "agosto de 2022 ", "Autenticacao": "x4fv2s4v908q", "TipoVeiculo": 1, "SiglaCombustivel": "G", "DataConsulta": "terça-feira, 4 de abril de 2023 00:15", "codigoTipoVeiculo": 1, "codigoMesReferencia": 288, "codigoMarca": 149, "codigoModelo": 4890, "codigoTipoCombustivel": 1}, {"Valor": "R$ 44.270,00", "Marca": "Fibravan", "Modelo": "Buggy Off Road 1.8 8V", "AnoModelo": 2018, "Combustivel": "Gasolina", "CodigoFipe": "067004-9", "MesReferencia": "agosto de 2022 ", "Autenticacao": "v2c7dw5l2w5h", "TipoVeiculo": 1, "SiglaCombustivel": "G", "DataConsulta": "terça-feira, 4 de abril de 2023 00:15", "codigoTipoVeiculo": 1, "codigoMesReferencia": 288, "codigoMarca": 149, "codigoModelo": 4890, "codigoTipoCombustivel": 1}, {"Valor": "R$ 38.003,00", "Marca": "Fibravan", "Modelo": "Buggy Off Road 1.8 8V", "AnoModelo": 2017, "Combustivel": "Gasolina", "CodigoFipe": "067004-9", "MesReferencia": "agosto de 2022 ", "Autenticacao": "spxcmcd55218", "TipoVeiculo": 1, "SiglaCombustivel": "G", "DataConsulta": "terça-feira, 4 de abril de 2023 00:15", "codigoTipoVeiculo": 1, "codigoMesReferencia": 288, "codigoMarca": 149, "codigoModelo": 4890, "codigoTipoCombustivel": 1}, {"Valor": "R$ 32.770,00", "Marca": "Fibravan", "Modelo": "Buggy Off Road 1.8 8V", "AnoModelo": 2016, "Combustivel": "Gasolina", "CodigoFipe": "067004-9", "MesReferencia": "agosto de 2022 ", "Autenticacao": "qqkbg4zsh1y1", "TipoVeiculo": 1, "SiglaCombustivel": "G", "DataConsulta": "terça-feira, 4 de abril de 2023 00:15", "codigoTipoVeiculo": 1, "codigoMesReferencia": 288, "codigoMarca": 149, "codigoModelo": 4890, "codigoTipoCombustivel": 1}, {"Valor": "R$ 30.567,00", "Marca": "Fibravan", "Modelo": "Buggy Off Road 1.8 8V", "AnoModelo": 2015, "Combustivel": "Gasolina", "CodigoFipe": "067004-9", "MesReferencia": "agosto de 2022 ", "Autenticacao": "pwql1rldjqvt", "TipoVeiculo": 1, "SiglaCombustivel": "G", "DataConsulta": "terça-feira, 4 de abril de 2023 00:15", "codigoTipoVeiculo": 1, "codigoMesReferencia": 288, "codigoMarca": 149, "codigoModelo": 4890, "codigoTipoCombustivel": 1}, {"Valor": "R$ 29.544,00", "Marca": "Fibravan", "Modelo": "Buggy Off Road 1.8 8V", "AnoModelo": 2014, "Combustivel": "Gasolina", "CodigoFipe": "067004-9", "MesReferencia": "agosto de 2022 ", "Autenticacao": "phqsbnmp6qrl", "TipoVeiculo": 1, "SiglaCombustivel": "G", "DataConsulta": "terça-feira, 4 de abril de 2023 00:15", "codigoTipoVeiculo": 1, "codigoMesReferencia": 288, "codigoMarca": 149, "codigoModelo": 4890, "codigoTipoCombustivel": 1}, {"Valor": "R$ 28.467,00", "Marca": "Fibravan", "Modelo": "Buggy Off Road 1.8 8V", "AnoModelo": 2013, "Combustivel": "Gasolina", "CodigoFipe": "067004-9", "MesReferencia": "agosto de 2022 ", "Autenticacao": "n2295ny8n0nc", "TipoVeiculo": 1, "SiglaCombustivel": "G", "DataConsulta": "terça-feira, 4 de abril de 2023 00:15", "codigoTipoVeiculo": 1, "codigoMesReferencia": 288, "codigoMarca": 149, "codigoModelo": 4890, "codigoTipoCombustivel": 1}, {"Valor": "R$ 24.705,00", "Marca": "Fibravan", "Modelo": "Buggy Off Road 1.8 8V", "AnoModelo": 2012, "Combustivel": "Gasolina", "CodigoFipe": "067004-9", "MesReferencia": "agosto de 2022 ", "Autenticacao": "mnzymd2277j4", "TipoVeiculo": 1, "SiglaCombustivel": "G", "DataConsulta": "terça-feira, 4 de abril de 2023 00:15", "codigoTipoVeiculo": 1, "codigoMesReferencia": 288, "codigoMarca": 149, "codigoModelo": 4890, "codigoTipoCombustivel": 1}, {"Valor": "R$ 22.287,00", "Marca": "Fibravan", "Modelo": "Buggy Off Road 1.8 8V", "AnoModelo": 2011, "Combustivel": "Gasolina", "CodigoFipe": "067004-9", "MesReferencia": "agosto de 2022 ", "Autenticacao": "lrm2nq0kn7fx", "TipoVeiculo": 1, "SiglaCombustivel": "G", "DataConsulta": "terça-feira, 4 de abril de 2023 00:15", "codigoTipoVeiculo": 1, "codigoMesReferencia": 288, "codigoMarca": 149, "codigoModelo": 4890, "codigoTipoCombustivel": 1}, {"Valor": "R$ 20.195,00", "Marca": "Fibravan", "Modelo": "Buggy Off Road 1.8 8V", "AnoModelo": 2010, "Combustivel": "Gasolina", "CodigoFipe": "067004-9", "MesReferencia": "agosto de 2022 ", "Autenticacao": "ky3px0c6xtp", "TipoVeiculo": 1, "SiglaCombustivel": "G", "DataConsulta": "terça-feira, 4 de abril de 2023 00:15", "codigoTipoVeiculo": 1, "codigoMesReferencia": 288, "codigoMarca": 149, "codigoModelo": 4890, "codigoTipoCombustivel": 1}, {"Valor": "R$ 18.531,00", "Marca": "Fibravan", "Modelo": "Buggy Off Road 1.8 8V", "AnoModelo": 2009, "Combustivel": "Gasolina", "CodigoFipe": "067004-9", "MesReferencia": "agosto de 2022 ", "Autenticacao": "kblwp7wgvd8q", "TipoVeiculo": 1, "SiglaCombustivel": "G", "DataConsulta": "terça-feira, 4 de abril de 2023 00:15", "codigoTipoVeiculo": 1, "codigoMesReferencia": 288, "codigoMarca": 149, "codigoModelo": 4890, "codigoTipoCombustivel": 1}, {"Valor": "R$ 81.102,00", "Marca": "Fibravan", "Modelo": "Buggy Plus 1.6 8V", "AnoModelo": 32000, "Combustivel": "Gasolina", "CodigoFipe": "067001-4", "MesReferencia": "agosto de 2022 ", "Autenticacao": "9z7j4hw0hrp", "TipoVeiculo": 1, "SiglaCombustivel": "G", "DataConsulta": "terça-feira, 4 de abril de 2023 00:15", "codigoTipoVeiculo": 1, "codigoMesReferencia": 288, "codigoMarca": 149, "codigoModelo": 4659, "codigoTipoCombustivel": 1}, {"Valor": "R$ 74.208,00", "Marca": "Fibravan", "Modelo": "Buggy Plus 1.6 8V", "AnoModelo": 2023, "Combustivel": "Gasolina", "CodigoFipe": "067001-4", "MesReferencia": "agosto de 2022 ", "Autenticacao": "7ddslfbdd0nc", "TipoVeiculo": 1, "SiglaCombustivel": "G", "DataConsulta": "terça-feira, 4 de abril de 2023 00:15", "codigoTipoVeiculo": 1, "codigoMesReferencia": 288, "codigoMarca": 149, "codigoModelo": 4659, "codigoTipoCombustivel": 1}, {"Valor": "R$ 69.997,00", "Marca": "Fibravan", "Modelo": "Buggy Plus 1.6 8V", "AnoModelo": 2022, "Combustivel": "Gasolina", "CodigoFipe": "067001-4", "MesReferencia": "agosto de 2022 ", "Autenticacao": "5s06w0qtstj4", "TipoVeiculo": 1, "SiglaCombustivel": "G", "DataConsulta": "terça-feira, 4 de abril de 2023 00:15", "codigoTipoVeiculo": 1, "codigoMesReferencia": 288, "codigoMarca": 149, "codigoModelo": 4659, "codigoTipoCombustivel": 1}, {"Valor": "R$ 61.033,00", "Marca": "Fibravan", "Modelo": "Buggy Plus 1.6 8V", "AnoModelo": 2021, "Combustivel": "Gasolina", "CodigoFipe": "067001-4", "MesReferencia": "agosto de 2022 ", "Autenticacao": "2dx2hn8hv0fx", "TipoVeiculo": 1, "SiglaCombustivel": "G", "DataConsulta": "terça-feira, 4 de abril de 2023 00:15", "codigoTipoVeiculo": 1, "codigoMesReferencia": 288, "codigoMarca": 149, "codigoModelo": 4659, "codigoTipoCombustivel": 1}, {"Valor": "R$ 45.697,00", "Marca": "Fibravan", "Modelo": "Buggy Plus 1.6 8V", "AnoModelo": 2020, "Combustivel": "Gasolina", "CodigoFipe": "067001-4", "MesReferencia": "agosto de 2022 ", "Autenticacao": "wl3w6w0tdgp", "TipoVeiculo": 1, "SiglaCombustivel": "G", "DataConsulta": "terça-feira, 4 de abril de 2023 00:15", "codigoTipoVeiculo": 1, "codigoMesReferencia": 288, "codigoMarca": 149, "codigoModelo": 4659, "codigoTipoCombustivel": 1}, {"Valor": "R$ 42.108,00", "Marca": "Fibravan", "Modelo": "Buggy Plus 1.6 8V", "AnoModelo": 2019, "Combustivel": "Gasolina", "CodigoFipe": "067001-4", "MesReferencia": "agosto de 2022 ", "Autenticacao": "t71dykl6jk8q", "TipoVeiculo": 1, "SiglaCombustivel": "G", "DataConsulta": "terça-feira, 4 de abril de 2023 00:15", "codigoTipoVeiculo": 1, "codigoMesReferencia": 288, "codigoMarca": 149, "codigoModelo": 4659, "codigoTipoCombustivel": 1}, {"Valor": "R$ 40.843,00", "Marca": "Fibravan", "Modelo": "Buggy Plus 1.6 8V", "AnoModelo": 2018, "Combustivel": "Gasolina", "CodigoFipe": "067001-4", "MesReferencia": "agosto de 2022 ", "Autenticacao": "tr6mg7mhhj5h", "TipoVeiculo": 1, "SiglaCombustivel": "G", "DataConsulta": "terça-feira, 4 de abril de 2023 00:15", "codigoTipoVeiculo": 1, "codigoMesReferencia": 288, "codigoMarca": 149, "codigoModelo": 4659, "codigoTipoCombustivel": 1}, {"Valor": "R$ 33.393,00", "Marca": "Fibravan", "Modelo": "Buggy Plus 1.6 8V", "AnoModelo": 2017, "Combustivel": "Gasolina", "CodigoFipe": "067001-4", "MesReferencia": "agosto de 2022 ", "Autenticacao": "qyvr5h1t4x18", "TipoVeiculo": 1, "SiglaCombustivel": "G", "DataConsulta": "terça-feira, 4 de abril de 2023 00:15", "codigoTipoVeiculo": 1, "codigoMesReferencia": 288, "codigoMarca": 149, "codigoModelo": 4659, "codigoTipoCombustivel": 1}, {"Valor": "R$ 30.918,00", "Marca": "Fibravan", "Modelo": "Buggy Plus 1.6 8V", "AnoModelo": 2016, "Combustivel": "Gasolina", "CodigoFipe": "067001-4", "MesReferencia": "agosto de 2022 ", "Autenticacao": "p0t5y1w0kqy1", "TipoVeiculo": 1, "SiglaCombustivel": "G", "DataConsulta": "terça-feira, 4 de abril de 2023 00:15", "codigoTipoVeiculo": 1, "codigoMesReferencia": 288, "codigoMarca": 149, "codigoModelo": 4659, "codigoTipoCombustivel": 1}, {"Valor": "R$ 27.314,00", "Marca": "Fibravan", "Modelo": "Buggy Plus 1.6 8V", "AnoModelo": 2015, "Combustivel": "Gasolina", "CodigoFipe": "067001-4", "MesReferencia": "agosto de 2022 ", "Autenticacao": "nnk7n9mprfvt", "TipoVeiculo": 1, "SiglaCombustivel": "G", "DataConsulta": "terça-feira, 4 de abril de 2023 00:15", "codigoTipoVeiculo": 1, "codigoMesReferencia": 288, "codigoMarca": 149, "codigoModelo": 4659, "codigoTipoCombustivel": 1}, {"Valor": "R$ 26.358,00", "Marca": "Fibravan", "Modelo": "Buggy Plus 1.6 8V", "AnoModelo": 2014, "Combustivel": "Gasolina", "CodigoFipe": "067001-4", "MesReferencia": "agosto de 2022 ", "Autenticacao": "m9crwxzr17rl", "TipoVeiculo": 1, "SiglaCombustivel": "G", "DataConsulta": "terça-feira, 4 de abril de 2023 00:15", "codigoTipoVeiculo": 1, "codigoMesReferencia": 288, "codigoMarca": 149, "codigoModelo": 4659, "codigoTipoCombustivel": 1}, {"Valor": "R$ 25.539,00", "Marca": "Fibravan", "Modelo": "Buggy Plus 1.6 8V", "AnoModelo": 2013, "Combustivel": "Gasolina", "CodigoFipe": "067001-4", "MesReferencia": "agosto de 2022 ", "Autenticacao": "mzr2rwbxf4nc", "TipoVeiculo": 1, "SiglaCombustivel": "G", "DataConsulta": "terça-feira, 4 de abril de 2023 00:15", "codigoTipoVeiculo": 1, "codigoMesReferencia": 288, "codigoMarca": 149, "codigoModelo": 4659, "codigoTipoCombustivel": 1}, {"Valor": "R$ 24.114,00", "Marca": "Fibravan", "Modelo": "Buggy Plus 1.6 8V", "AnoModelo": 2012, "Combustivel": "Gasolina", "CodigoFipe": "067001-4", "MesReferencia": "agosto de 2022 ", "Autenticacao": "mf14hghm89j4", "TipoVeiculo": 1, "SiglaCombustivel": "G", "DataConsulta": "terça-feira, 4 de abril de 2023 00:15", "codigoTipoVeiculo": 1, "codigoMesReferencia": 288, "codigoMarca": 149, "codigoModelo": 4659, "codigoTipoCombustivel": 1}, {"Valor": "R$ 20.956,00", "Marca": "Fibravan", "Modelo": "Buggy Plus 1.6 8V", "AnoModelo": 2011, "Combustivel": "Gasolina", "CodigoFipe": "067001-4", "MesReferencia": "agosto de 2022 ", "Autenticacao": "k709jzk5wyfx", "TipoVeiculo": 1, "SiglaCombustivel": "G", "DataConsulta": "terça-feira, 4 de abril de 2023 00:15", "codigoTipoVeiculo": 1, "codigoMesReferencia": 288, "codigoMarca": 149, "codigoModelo": 4659, "codigoTipoCombustivel": 1}, {"Valor": "R$ 15.381,00", "Marca": "Fibravan", "Modelo": "Buggy Plus 1.6 8V", "AnoModelo": 2010, "Combustivel": "Gasolina", "CodigoFipe": "067001-4", "MesReferencia": "agosto de 2022 ", "Autenticacao": "h4nyw3p05rp", "TipoVeiculo": 1, "SiglaCombustivel": "G", "DataConsulta": "terça-feira, 4 de abril de 2023 00:15", "codigoTipoVeiculo": 1, "codigoMesReferencia": 288, "codigoMarca": 149, "codigoModelo": 4659, "codigoTipoCombustivel": 1}, {"Valor": "R$ 13.395,00", "Marca": "Fibravan", "Modelo": "Buggy Plus 1.6 8V", "AnoModelo": 2009, "Combustivel": "Gasolina", "CodigoFipe": "067001-4", "MesReferencia": "agosto de 2022 ", "Autenticacao": "hdc3jk7hbd8q", "TipoVeiculo": 1, "SiglaCombustivel": "G", "DataConsulta": "terça-feira, 4 de abril de 2023 00:15", "codigoTipoVeiculo": 1, "codigoMesReferencia": 288, "codigoMarca": 149, "codigoModelo": 4659, "codigoTipoCombustivel": 1}, {"Valor": "R$ 11.719,00", "Marca": "Fibravan", "Modelo": "Buggy Plus 1.6 8V", "AnoModelo": 2008, "Combustivel": "Gasolina", "CodigoFipe": "067001-4", "MesReferencia": "agosto de 2022 ", "Autenticacao": "grqx287k225h", "TipoVeiculo": 1, "SiglaCombustivel": "G", "DataConsulta": "terça-feira, 4 de abril de 2023 00:15", "codigoTipoVeiculo": 1, "codigoMesReferencia": 288, "codigoMarca": 149, "codigoModelo": 4659, "codigoTipoCombustivel": 1}, {"Valor": "R$ 31.954,00", "Marca": "Fibravan", "Modelo": "Buggy Vip 1.6 8V Total Flex", "AnoModelo": 2015, "Combustivel": "Gasolina", "CodigoFipe": "067003-0", "MesReferencia": "agosto de 2022 ", "Autenticacao": "qdzq4zgrb2vt", "TipoVeiculo": 1, "SiglaCombustivel": "G", "DataConsulta": "terça-feira, 4 de abril de 2023 00:15", "codigoTipoVeiculo": 1, "codigoMesReferencia": 288, "codigoMarca": 149, "codigoModelo": 4660, "codigoTipoCombustivel": 1}, {"Valor": "R$ 30.802,00", "Marca": "Fibravan", "Modelo": "Buggy Vip 1.6 8V Total Flex", "AnoModelo": 2014, "Combustivel": "Gasolina", "CodigoFipe": "067003-0", "MesReferencia": "agosto de 2022 ", "Autenticacao": "pzg0xxhr18rl", "TipoVeiculo": 1, "SiglaCombustivel": "G", "DataConsulta": "terça-feira, 4 de abril de 2023 00:15", "codigoTipoVeiculo": 1, "codigoMesReferencia": 288, "codigoMarca": 149, "codigoModelo": 4660, "codigoTipoCombustivel": 1}, {"Valor": "R$ 28.985,00", "Marca": "Fibravan", "Modelo": "Buggy Vip 1.6 8V Total Flex", "AnoModelo": 2013, "Combustivel": "Gasolina", "CodigoFipe": "067003-0", "MesReferencia": "agosto de 2022 ", "Autenticacao": "n85lr30dp6nc", "TipoVeiculo": 1, "SiglaCombustivel": "G", "DataConsulta": "terça-feira, 4 de abril de 2023 00:15", "codigoTipoVeiculo": 1, "codigoMesReferencia": 288, "codigoMarca": 149, "codigoModelo": 4660, "codigoTipoCombustivel": 1}, {"Valor": "R$ 25.754,00", "Marca": "Fibravan", "Modelo": "Buggy Vip 1.6 8V Total Flex", "AnoModelo": 2012, "Combustivel": "Gasolina", "CodigoFipe": "067003-0", "MesReferencia": "agosto de 2022 ", "Autenticacao": "m186840222j4", "TipoVeiculo": 1, "SiglaCombustivel": "G", "DataConsulta": "terça-feira, 4 de abril de 2023 00:15", "codigoTipoVeiculo": 1, "codigoMesReferencia": 288, "codigoMarca": 149, "codigoModelo": 4660, "codigoTipoCombustivel": 1}, {"Valor": "R$ 23.547,00", "Marca": "Fibravan", "Modelo": "Buggy Vip 1.6 8V Total Flex", "AnoModelo": 2011, "Combustivel": "Gasolina", "CodigoFipe": "067003-0", "MesReferencia": "agosto de 2022 ", "Autenticacao": "l7d1sk3913fx", "TipoVeiculo": 1, "SiglaCombustivel": "G", "DataConsulta": "terça-feira, 4 de abril de 2023 00:15", "codigoTipoVeiculo": 1, "codigoMesReferencia": 288, "codigoMarca": 149, "codigoModelo": 4660, "codigoTipoCombustivel": 1}, {"Valor": "R$ 20.645,00", "Marca": "Fibravan", "Modelo": "Buggy Vip 1.6 8V Total Flex", "AnoModelo": 2010, "Combustivel": "Gasolina", "CodigoFipe": "067003-0", "MesReferencia": "agosto de 2022 ", "Autenticacao": "k4c8bfzq11p", "TipoVeiculo": 1, "SiglaCombustivel": "G", "DataConsulta": "terça-feira, 4 de abril de 2023 00:15", "codigoTipoVeiculo": 1, "codigoMesReferencia": 288, "codigoMarca": 149, "codigoModelo": 4660, "codigoTipoCombustivel": 1}, {"Valor": "R$ 19.862,00", "Marca": "Fibravan", "Modelo": "Buggy Vip 1.6 8V Total Flex", "AnoModelo": 2009, "Combustivel": "Gasolina", "CodigoFipe": "067003-0", "MesReferencia": "agosto de 2022 ", "Autenticacao": "kt6ntztcxq8q", "TipoVeiculo": 1, "SiglaCombustivel": "G", "DataConsulta": "terça-feira, 4 de abril de 2023 00:15", "codigoTipoVeiculo": 1, "codigoMesReferencia": 288, "codigoMarca": 149, "codigoModelo": 4660, "codigoTipoCombustivel": 1}, {"Valor": "R$ 17.374,00", "Marca": "Fibravan", "Modelo": "Buggy Vip 1.6 8V Total Flex", "AnoModelo": 2008, "Combustivel": "Gasolina", "CodigoFipe": "067003-0", "MesReferencia": "agosto de 2022 ", "Autenticacao": "jw1b4p1jxf5h", "TipoVeiculo": 1, "SiglaCombustivel": "G", "DataConsulta": "terça-feira, 4 de abril de 2023 00:15", "codigoTipoVeiculo": 1, "codigoMesReferencia": 288, "codigoMarca": 149, "codigoModelo": 4660, "codigoTipoCombustivel": 1}, {"Valor": "R$ 94.101,00", "Marca": "Fibravan", "Modelo": "Buggy Vip 1.8 8V", "AnoModelo": 32000, "Combustivel": "Gasolina", "CodigoFipe": "067002-2", "MesReferencia": "agosto de 2022 ", "Autenticacao": "cgxm84f3vswp", "TipoVeiculo": 1, "SiglaCombustivel": "G", "DataConsulta": "terça-feira, 4 de abril de 2023 00:15", "codigoTipoVeiculo": 1, "codigoMesReferencia": 288, "codigoMarca": 149, "codigoModelo": 4661, "codigoTipoCombustivel": 1}, {"Valor": "R$ 85.451,00", "Marca": "Fibravan", "Modelo": "Buggy Vip 1.8 8V", "AnoModelo": 2023, "Combustivel": "Gasolina", "CodigoFipe": "067002-2", "MesReferencia": "agosto de 2022 ", "Autenticacao": "ccm68rjmkdxnc", "TipoVeiculo": 1, "SiglaCombustivel": "G", "DataConsulta": "terça-feira, 4 de abril de 2023 00:15", "codigoTipoVeiculo": 1, "codigoMesReferencia": 288, "codigoMarca": 149, "codigoModelo": 4661, "codigoTipoCombustivel": 1}, {"Valor": "R$ 79.022,00", "Marca": "Fibravan", "Modelo": "Buggy Vip 1.8 8V", "AnoModelo": 2022, "Combustivel": "Gasolina", "CodigoFipe": "067002-2", "MesReferencia": "agosto de 2022 ", "Autenticacao": "86vjl9rwvzj4", "TipoVeiculo": 1, "SiglaCombustivel": "G", "DataConsulta": "terça-feira, 4 de abril de 2023 00:15", "codigoTipoVeiculo": 1, "codigoMesReferencia": 288, "codigoMarca": 149, "codigoModelo": 4661, "codigoTipoCombustivel": 1}, {"Valor": "R$ 70.789,00", "Marca": "Fibravan", "Modelo": "Buggy Vip 1.8 8V", "AnoModelo": 2021, "Combustivel": "Gasolina", "CodigoFipe": "067002-2", "MesReferencia": "agosto de 2022 ", "Autenticacao": "5292s30wc2fx", "TipoVeiculo": 1, "SiglaCombustivel": "G", "DataConsulta": "terça-feira, 4 de abril de 2023 00:15", "codigoTipoVeiculo": 1, "codigoMesReferencia": 288, "codigoMarca": 149, "codigoModelo": 4661, "codigoTipoCombustivel": 1}, {"Valor": "R$ 51.180,00", "Marca": "Fibravan", "Modelo": "Buggy Vip 1.8 8V", "AnoModelo": 2020, "Combustivel": "Gasolina", "CodigoFipe": "067002-2", "MesReferencia": "agosto de 2022 ", "Autenticacao": "ypds7pg2zbp", "TipoVeiculo": 1, "SiglaCombustivel": "G", "DataConsulta": "terça-feira, 4 de abril de 2023 00:15", "codigoTipoVeiculo": 1, "codigoMesReferencia": 288, "codigoMarca": 149, "codigoModelo": 4661, "codigoTipoCombustivel": 1}, {"Valor": "R$ 44.839,00", "Marca": "Fibravan", "Modelo": "Buggy Vip 1.8 8V", "AnoModelo": 2019, "Combustivel": "Gasolina", "CodigoFipe": "067002-2", "MesReferencia": "agosto de 2022 ", "Autenticacao": "v811ncjzlk8q", "TipoVeiculo": 1, "SiglaCombustivel": "G", "DataConsulta": "terça-feira, 4 de abril de 2023 00:15", "codigoTipoVeiculo": 1, "codigoMesReferencia": 288, "codigoMarca": 149, "codigoModelo": 4661, "codigoTipoCombustivel": 1}, {"Valor": "R$ 41.120,00", "Marca": "Fibravan", "Modelo": "Buggy Vip 1.8 8V", "AnoModelo": 2018, "Combustivel": "Gasolina", "CodigoFipe": "067002-2", "MesReferencia": "agosto de 2022 ", "Autenticacao": "twf9lrz7hq5h", "TipoVeiculo": 1, "SiglaCombustivel": "G", "DataConsulta": "terça-feira, 4 de abril de 2023 00:15", "codigoTipoVeiculo": 1, "codigoMesReferencia": 288, "codigoMarca": 149, "codigoModelo": 4661, "codigoTipoCombustivel": 1}, {"Valor": "R$ 35.480,00", "Marca": "Fibravan", "Modelo": "Buggy Vip 1.8 8V", "AnoModelo": 2017, "Combustivel": "Gasolina", "CodigoFipe": "067002-2", "MesReferencia": "agosto de 2022 ", "Autenticacao": "rrbbkr10n118", "TipoVeiculo": 1, "SiglaCombustivel": "G", "DataConsulta": "terça-feira, 4 de abril de 2023 00:15", "codigoTipoVeiculo": 1, "codigoMesReferencia": 288, "codigoMarca": 149, "codigoModelo": 4661, "codigoTipoCombustivel": 1}, {"Valor": "R$ 29.741,00", "Marca": "Fibravan", "Modelo": "Buggy Vip 1.8 8V", "AnoModelo": 2015, "Combustivel": "Gasolina", "CodigoFipe": "067002-2", "MesReferencia": "agosto de 2022 ", "Autenticacao": "pk1c1mtxsdvt", "TipoVeiculo": 1, "SiglaCombustivel": "G", "DataConsulta": "terça-feira, 4 de abril de 2023 00:15", "codigoTipoVeiculo": 1, "codigoMesReferencia": 288, "codigoMarca": 149, "codigoModelo": 4661, "codigoTipoCombustivel": 1}, {"Valor": "R$ 28.629,00", "Marca": "Fibravan", "Modelo": "Buggy Vip 1.8 8V", "AnoModelo": 2014, "Combustivel": "Gasolina", "CodigoFipe": "067002-2", "MesReferencia": "agosto de 2022 ", "Autenticacao": "n4z6jbtt01rl", "TipoVeiculo": 1, "SiglaCombustivel": "G", "DataConsulta": "terça-feira, 4 de abril de 2023 00:15", "codigoTipoVeiculo": 1, "codigoMesReferencia": 288, "codigoMarca": 149, "codigoModelo": 4661, "codigoTipoCombustivel": 1}, {"Valor": "R$ 27.014,00", "Marca": "Fibravan", "Modelo": "Buggy Vip 1.8 8V", "AnoModelo": 2013, "Combustivel": "Gasolina", "CodigoFipe": "067002-2", "MesReferencia": "agosto de 2022 ", "Autenticacao": "nj16d0dlvknc", "TipoVeiculo": 1, "SiglaCombustivel": "G", "DataConsulta": "terça-feira, 4 de abril de 2023 00:15", "codigoTipoVeiculo": 1, "codigoMesReferencia": 288, "codigoMarca": 149, "codigoModelo": 4661, "codigoTipoCombustivel": 1}, {"Valor": "R$ 24.546,00", "Marca": "Fibravan", "Modelo": "Buggy Vip 1.8 8V", "AnoModelo": 2012, "Combustivel": "Gasolina", "CodigoFipe": "067002-2", "MesReferencia": "agosto de 2022 ", "Autenticacao": "ml342l3p3hj4", "TipoVeiculo": 1, "SiglaCombustivel": "G", "DataConsulta": "terça-feira, 4 de abril de 2023 00:15", "codigoTipoVeiculo": 1, "codigoMesReferencia": 288, "codigoMarca": 149, "codigoModelo": 4661, "codigoTipoCombustivel": 1}, {"Valor": "R$ 21.862,00", "Marca": "Fibravan", "Modelo": "Buggy Vip 1.8 8V", "AnoModelo": 2011, "Combustivel": "Gasolina", "CodigoFipe": "067002-2", "MesReferencia": "agosto de 2022 ", "Autenticacao": "llnlym0thlfx", "TipoVeiculo": 1, "SiglaCombustivel": "G", "DataConsulta": "terça-feira, 4 de abril de 2023 00:15", "codigoTipoVeiculo": 1, "codigoMesReferencia": 288, "codigoMarca": 149, "codigoModelo": 4661, "codigoTipoCombustivel": 1}, {"Valor": "R$ 19.800,00", "Marca": "Fibravan", "Modelo": "Buggy Vip 1.8 8V", "AnoModelo": 2010, "Combustivel": "Gasolina", "CodigoFipe": "067002-2", "MesReferencia": "agosto de 2022 ", "Autenticacao": "ktg37q3wm0p", "TipoVeiculo": 1, "SiglaCombustivel": "G", "DataConsulta": "terça-feira, 4 de abril de 2023 00:15", "codigoTipoVeiculo": 1, "codigoMesReferencia": 288, "codigoMarca": 149, "codigoModelo": 4661, "codigoTipoCombustivel": 1}, {"Valor": "R$ 17.713,00", "Marca": "Fibravan", "Modelo": "Buggy Vip 1.8 8V", "AnoModelo": 2009, "Combustivel": "Gasolina", "CodigoFipe": "067002-2", "MesReferencia": "agosto de 2022 ", "Autenticacao": "j00kvg3r6c8q", "TipoVeiculo": 1, "SiglaCombustivel": "G", "DataConsulta": "terça-feira, 4 de abril de 2023 00:15", "codigoTipoVeiculo": 1, "codigoMesReferencia": 288, "codigoMarca": 149, "codigoModelo": 4661, "codigoTipoCombustivel": 1}, {"Valor": "R$ 13.800,00", "Marca": "Fibravan", "Modelo": "Buggy Vip 1.8 8V", "AnoModelo": 2008, "Combustivel": "Gasolina", "CodigoFipe": "067002-2", "MesReferencia": "agosto de 2022 ", "Autenticacao": "hj39wshn075h", "TipoVeiculo": 1, "SiglaCombustivel": "G", "DataConsulta": "terça-feira, 4 de abril de 2023 00:15", "codigoTipoVeiculo": 1, "codigoMesReferencia": 288, "codigoMarca": 149, "codigoModelo": 4661, "codigoTipoCombustivel": 1}]